{"total":{"value":779,"relation":"eq"},"id_modelos":[{"id_modelo":"140293542","nombre_modelo":"Redmi Note 12 Pro 6GB\/128GB 6.67\u00b4\u00b4 Dual Sim","nombre_modelo_eng":"Redmi Note 12 Pro 6GB\/128GB 6.67\u00b4\u00b4 Dual Sim","marca":"Xiaomi","sostenible":0,"productes":[{"brut":"181.20","v360":null,"talla":null,"color":null,"v180":null,"talla2":null,"talla_usa":null,"talla_uk":null,"talla_jp":null,"stock_reservat":1,"v90":null,"desc_brand":"0.00","exist":0,"rec":"279.13","pmp":"181.20","v30":null,"id_producte":"141066131","baja":"0","referencia":"NOTE12P 4G 6-128 BL","sellers":[]}],"familias":null,"video_mp4":0,"fecha_descatalogado":"2078-12-31T00:00:00","image_created":null,"tres_sesenta":"0","precio_win":210.99,"id_pos_producte_win":0,"id_marca":"2696","precio_tachado":0,"list_atributos":""},{"id_modelo":"140392826","nombre_modelo":"Armor 14 Pro 8GB\/128GB 6.5\u00b4\u00b4","nombre_modelo_eng":"Armor 14 Pro 8GB\/128GB 6.5\u00b4\u00b4","marca":"Ulefone","sostenible":0,"productes":[{"brut":"169.96","v360":null,"talla":null,"color":null,"v180":null,"talla2":null,"talla_usa":null,"talla_uk":null,"talla_jp":null,"stock_reservat":1,"v90":null,"desc_brand":"0.00","exist":0,"rec":"263.28","pmp":"169.96","v30":null,"id_producte":"141353988","baja":"0","referencia":"ULEAR14PROB8","sellers":[]}],"familias":null,"video_mp4":0,"fecha_descatalogado":"2078-12-31T00:00:00","image_created":null,"tres_sesenta":"0","precio_win":210.99,"id_pos_producte_win":0,"id_marca":"6373","precio_tachado":0,"list_atributos":""},{"id_modelo":"139594773","nombre_modelo":"Galaxy M33 5G 6GB\/128GB 6.6\u00b4\u00b4 Dual Sim","nombre_modelo_eng":"Galaxy M33 5G 6GB\/128GB 6.6\u00b4\u00b4 Dual Sim","marca":"Samsung","sostenible":0,"productes":[{"brut":"177.45","v360":null,"talla":null,"color":null,"v180":null,"talla2":null,"talla_usa":null,"talla_uk":null,"talla_jp":null,"stock_reservat":0,"v90":null,"desc_brand":"0.00","exist":0,"rec":"339.86","pmp":"177.45","v30":null,"id_producte":"18732611","baja":"0","referencia":"TKOSA1SZA1145","sellers":[]}],"familias":null,"video_mp4":0,"fecha_descatalogado":"2078-12-31T00:00:00","image_created":null,"tres_sesenta":"0","precio_win":211.49,"id_pos_producte_win":0,"id_marca":"2947","precio_tachado":0,"list_atributos":""},{"id_modelo":"139744694","nombre_modelo":"Galaxy A23 5G 4GB\/128GB 6.6\u00b4\u00b4 Dual Sim","nombre_modelo_eng":"Galaxy A23 5G 4GB\/128GB 6.6\u00b4\u00b4 Dual Sim","marca":"Samsung","sostenible":0,"productes":[{"brut":"179.70","v360":null,"talla":null,"color":null,"v180":null,"talla2":null,"talla_usa":null,"talla_uk":null,"talla_jp":null,"stock_reservat":0,"v90":null,"desc_brand":"0.00","exist":0,"rec":"305.57","pmp":"179.70","v30":null,"id_producte":"19334076","baja":"0","referencia":"A236 4-128 WH","sellers":[]}],"familias":null,"video_mp4":0,"fecha_descatalogado":"2078-12-31T00:00:00","image_created":null,"tres_sesenta":"0","precio_win":211.49,"id_pos_producte_win":0,"id_marca":"2947","precio_tachado":0,"list_atributos":""},{"id_modelo":"139776836","nombre_modelo":"Galaxy A23 EE 5G 4GB\/128GB 6.8\u00b4\u00b4 Dual Sim","nombre_modelo_eng":"Galaxy A23 EE 5G 4GB\/128GB 6.8\u00b4\u00b4 Dual Sim","marca":"Samsung","sostenible":0,"productes":[{"brut":"172.99","v360":null,"talla":null,"color":null,"v180":null,"talla2":null,"talla_usa":null,"talla_uk":null,"talla_jp":null,"stock_reservat":0,"v90":null,"desc_brand":"0.00","exist":0,"rec":"405.86","pmp":"172.99","v30":null,"id_producte":"19473278","baja":"0","referencia":"SM-A236BZKVEEB","sellers":[]}],"familias":null,"video_mp4":0,"fecha_descatalogado":"2078-12-31T00:00:00","image_created":null,"tres_sesenta":"0","precio_win":211.99,"id_pos_producte_win":0,"id_marca":"2947","precio_tachado":0,"list_atributos":""},{"id_modelo":"139861454","nombre_modelo":"Redmi Note 12 5G 6GB\/128GB 6.67\u00b4\u00b4 Dual Sim","nombre_modelo_eng":"Redmi Note 12 5G 6GB\/128GB 6.67\u00b4\u00b4 Dual Sim","marca":"Xiaomi","sostenible":0,"productes":[{"brut":"181.25","v360":null,"talla":null,"color":null,"v180":null,"talla2":null,"talla_usa":null,"talla_uk":null,"talla_jp":null,"stock_reservat":0,"v90":null,"desc_brand":"0.00","exist":0,"rec":"287.67","pmp":"181.25","v30":null,"id_producte":"19725319","baja":"0","referencia":"MZB0CY8EU","sellers":[]}],"familias":null,"video_mp4":0,"fecha_descatalogado":"2078-12-31T00:00:00","image_created":null,"tres_sesenta":"0","precio_win":211.99,"id_pos_producte_win":0,"id_marca":"2696","precio_tachado":0,"list_atributos":""},{"id_modelo":"139632734","nombre_modelo":"Moto G82 6GB\/128GB 6.6\u00b4\u00b4 Dual Sim","nombre_modelo_eng":"Moto G82 6GB\/128GB 6.6\u00b4\u00b4 Dual Sim","marca":"Motorola","sostenible":0,"productes":[{"brut":"175.48","v360":null,"talla":null,"color":null,"v180":null,"talla2":null,"talla_usa":null,"talla_uk":null,"talla_jp":null,"stock_reservat":3,"v90":null,"desc_brand":"0.00","exist":0,"rec":"377.39","pmp":"175.48","v30":null,"id_producte":"18898141","baja":"0","referencia":"TKOMOTSZA0135","sellers":[]}],"familias":null,"video_mp4":0,"fecha_descatalogado":"2078-12-31T00:00:00","image_created":null,"tres_sesenta":"0","precio_win":211.99,"id_pos_producte_win":0,"id_marca":"2180","precio_tachado":0,"list_atributos":""},{"id_modelo":"139632735","nombre_modelo":"Moto G82 6GB\/128GB 6.6\u00b4\u00b4 Dual Sim","nombre_modelo_eng":"Moto G82 6GB\/128GB 6.6\u00b4\u00b4 Dual Sim","marca":"Motorola","sostenible":0,"productes":[{"brut":"175.48","v360":null,"talla":null,"color":null,"v180":null,"talla2":null,"talla_usa":null,"talla_uk":null,"talla_jp":null,"stock_reservat":1,"v90":null,"desc_brand":"0.00","exist":0,"rec":"377.39","pmp":"175.48","v30":null,"id_producte":"18898142","baja":"0","referencia":"TKOMOTSZA0134","sellers":[]}],"familias":null,"video_mp4":0,"fecha_descatalogado":"2078-12-31T00:00:00","image_created":null,"tres_sesenta":"0","precio_win":211.99,"id_pos_producte_win":0,"id_marca":"2180","precio_tachado":0,"list_atributos":""},{"id_modelo":"139899799","nombre_modelo":"POCO X5 5G 6GB\/128GB 6.67\u00b4\u00b4 Dual Sim","nombre_modelo_eng":"POCO X5 5G 6GB\/128GB 6.67\u00b4\u00b4 Dual Sim","marca":"Xiaomi","sostenible":0,"productes":[{"brut":"179.00","v360":null,"talla":null,"color":null,"v180":null,"talla2":null,"talla_usa":null,"talla_uk":null,"talla_jp":null,"stock_reservat":0,"v90":null,"desc_brand":"0.00","exist":0,"rec":"324.60","pmp":"179.00","v30":null,"id_producte":"19885945","baja":"0","referencia":"POCO X5 5G 6-128 BL","sellers":[]}],"familias":null,"video_mp4":0,"fecha_descatalogado":"2078-12-31T00:00:00","image_created":null,"tres_sesenta":"0","precio_win":211.99,"id_pos_producte_win":0,"id_marca":"2696","precio_tachado":0,"list_atributos":""},{"id_modelo":"139464330","nombre_modelo":"Galaxy A23 5G 4GB\/128GB 6.6\u00b4\u00b4 Dual Sim","nombre_modelo_eng":"Galaxy A23 5G 4GB\/128GB 6.6\u00b4\u00b4 Dual Sim","marca":"Samsung","sostenible":0,"productes":[{"brut":"175.87","v360":null,"talla":null,"color":null,"v180":null,"talla2":null,"talla_usa":null,"talla_uk":null,"talla_jp":null,"stock_reservat":0,"v90":null,"desc_brand":"0.00","exist":0,"rec":"390.18","pmp":"175.87","v30":null,"id_producte":"18167204","baja":"0","referencia":"7730631","sellers":[]}],"familias":null,"video_mp4":0,"fecha_descatalogado":"2078-12-31T00:00:00","image_created":null,"tres_sesenta":"0","precio_win":213.49,"id_pos_producte_win":0,"id_marca":"2947","precio_tachado":0,"list_atributos":""},{"id_modelo":"138221281","nombre_modelo":"Blade 3 4GB\/64GB 6.2\u00b4\u00b4 Dual Sim","nombre_modelo_eng":"Blade 3 4GB\/64GB 6.2\u00b4\u00b4 Dual Sim","marca":"Hammer","sostenible":0,"productes":[{"brut":"168.60","v360":null,"talla":null,"color":null,"v180":null,"talla2":null,"talla_usa":null,"talla_uk":null,"talla_jp":null,"stock_reservat":0,"v90":null,"desc_brand":"0.00","exist":0,"rec":"300.00","pmp":"168.60","v30":null,"id_producte":"13678673","baja":"0","referencia":"TLHABLADE3","sellers":[]}],"familias":null,"video_mp4":0,"fecha_descatalogado":"2078-12-31T00:00:00","image_created":null,"tres_sesenta":"0","precio_win":213.99,"id_pos_producte_win":0,"id_marca":"5337","precio_tachado":0,"list_atributos":""},{"id_modelo":"139562213","nombre_modelo":"V31D 3GB\/32GB 5.5\u00b4\u00b4 Dual Sim","nombre_modelo_eng":"V31D 3GB\/32GB 5.5\u00b4\u00b4 Dual Sim","marca":"Nomu","sostenible":0,"productes":[{"brut":"162.16","v360":null,"talla":null,"color":null,"v180":null,"talla2":null,"talla_usa":null,"talla_uk":null,"talla_jp":null,"stock_reservat":0,"v90":null,"desc_brand":"0.00","exist":3,"rec":"330.22","pmp":"165.11","v30":null,"id_producte":"18575462","baja":"0","referencia":"1357817","sellers":[]}],"familias":null,"video_mp4":0,"fecha_descatalogado":"2078-12-31T00:00:00","image_created":null,"tres_sesenta":"0","precio_win":213.99,"id_pos_producte_win":0,"id_marca":"7416","precio_tachado":0,"list_atributos":""},{"id_modelo":"139693272","nombre_modelo":"Galaxy A23 5G 4GB\/64GB 6.6\u00b4\u00b4 Dual Sim","nombre_modelo_eng":"Galaxy A23 5G 4GB\/64GB 6.6\u00b4\u00b4 Dual Sim","marca":"Samsung","sostenible":0,"productes":[{"brut":"176.06","v360":null,"talla":null,"color":null,"v180":null,"talla2":null,"talla_usa":null,"talla_uk":null,"talla_jp":null,"stock_reservat":0,"v90":null,"desc_brand":"0.00","exist":0,"rec":"419.52","pmp":"176.06","v30":null,"id_producte":"19126121","baja":"0","referencia":"A236 4-64 BK","sellers":[]}],"familias":null,"video_mp4":0,"fecha_descatalogado":"2078-12-31T00:00:00","image_created":null,"tres_sesenta":"0","precio_win":215.99,"id_pos_producte_win":0,"id_marca":"2947","precio_tachado":0,"list_atributos":""},{"id_modelo":"139369551","nombre_modelo":"G42 6GB\/128GB 6.4\u00b4\u00b4","nombre_modelo_eng":"G42 6GB\/128GB 6.4\u00b4\u00b4","marca":"Motorola","sostenible":0,"productes":[{"brut":"185.99","v360":null,"talla":null,"color":null,"v180":null,"talla2":null,"talla_usa":null,"talla_uk":null,"talla_jp":null,"stock_reservat":0,"v90":null,"desc_brand":"0.00","exist":1,"rec":"282.70","pmp":"185.99","v30":null,"id_producte":"17792697","baja":"0","referencia":"PAU00010ES","sellers":[]}],"familias":null,"video_mp4":0,"fecha_descatalogado":"2078-12-31T00:00:00","image_created":null,"tres_sesenta":"1","precio_win":216.49,"id_pos_producte_win":0,"id_marca":"2180","precio_tachado":0,"list_atributos":""},{"id_modelo":"139894360","nombre_modelo":"Moto G73 5G 8GB\/256GB 6.5\u00b4\u00b4 Dual Sim","nombre_modelo_eng":"Moto G73 5G 8GB\/256GB 6.5\u00b4\u00b4 Dual Sim","marca":"Motorola","sostenible":0,"productes":[{"brut":"174.84","v360":null,"talla":null,"color":null,"v180":null,"talla2":null,"talla_usa":null,"talla_uk":null,"talla_jp":null,"stock_reservat":10,"v90":null,"desc_brand":"0.00","exist":0,"rec":"459.80","pmp":"174.84","v30":null,"id_producte":"19842013","baja":"0","referencia":"PAUX0027SE","sellers":[]}],"familias":null,"video_mp4":0,"fecha_descatalogado":"2078-12-31T00:00:00","image_created":null,"tres_sesenta":"0","precio_win":217.49,"id_pos_producte_win":0,"id_marca":"2180","precio_tachado":0,"list_atributos":""},{"id_modelo":"139744715","nombre_modelo":"Redmi Note 11 Pro 6GB\/128GB 6.67\u00b4\u00b4 Dual Sim","nombre_modelo_eng":"Redmi Note 11 Pro 6GB\/128GB 6.67\u00b4\u00b4 Dual Sim","marca":"Xiaomi","sostenible":0,"productes":[{"brut":"184.90","v360":null,"talla":null,"color":null,"v180":null,"talla2":null,"talla_usa":null,"talla_uk":null,"talla_jp":null,"stock_reservat":1,"v90":null,"desc_brand":"0.00","exist":0,"rec":"333.12","pmp":"184.90","v30":null,"id_producte":"19334097","baja":"0","referencia":"MZB0ASKEU","sellers":[]}],"familias":null,"video_mp4":0,"fecha_descatalogado":"2078-12-31T00:00:00","image_created":null,"tres_sesenta":"0","precio_win":218.99,"id_pos_producte_win":0,"id_marca":"2696","precio_tachado":0,"list_atributos":""},{"id_modelo":"140227053","nombre_modelo":"90 Lite 5G 8GB\/256GB 6.7\u00b4\u00b4 Dual Sim","nombre_modelo_eng":"90 Lite 5G 8GB\/256GB 6.7\u00b4\u00b4 Dual Sim","marca":"Honor","sostenible":0,"productes":[{"brut":"183.41","v360":null,"talla":null,"color":null,"v180":null,"talla2":null,"talla_usa":null,"talla_uk":null,"talla_jp":null,"stock_reservat":4,"v90":null,"desc_brand":"0.00","exist":0,"rec":"363.36","pmp":"183.41","v30":null,"id_producte":"140821091","baja":"0","referencia":"5109ASWE","sellers":[]}],"familias":null,"video_mp4":0,"fecha_descatalogado":"2078-12-31T00:00:00","image_created":null,"tres_sesenta":"0","precio_win":219.49,"id_pos_producte_win":0,"id_marca":"4341","precio_tachado":0,"list_atributos":""},{"id_modelo":"140293538","nombre_modelo":"Redmi Note 12 5G 6GB\/128GB 6.67\u00b4\u00b4 Dual Sim","nombre_modelo_eng":"Redmi Note 12 5G 6GB\/128GB 6.67\u00b4\u00b4 Dual Sim","marca":"Xiaomi","sostenible":0,"productes":[{"brut":"189.59","v360":null,"talla":null,"color":null,"v180":null,"talla2":null,"talla_usa":null,"talla_uk":null,"talla_jp":null,"stock_reservat":0,"v90":null,"desc_brand":"0.00","exist":0,"rec":"288.18","pmp":"189.59","v30":null,"id_producte":"141066127","baja":"0","referencia":"MZB0CYPEU","sellers":[]}],"familias":null,"video_mp4":0,"fecha_descatalogado":"2078-12-31T00:00:00","image_created":null,"tres_sesenta":"0","precio_win":220.49,"id_pos_producte_win":0,"id_marca":"2696","precio_tachado":0,"list_atributos":""},{"id_modelo":"139464540","nombre_modelo":"Galaxy A23 4G\/64GB 6.6\u00b4\u00b4 Dual Sim","nombre_modelo_eng":"Galaxy A23 4G\/64GB 6.6\u00b4\u00b4 Dual Sim","marca":"Samsung","sostenible":0,"productes":[{"brut":"186.00","v360":null,"talla":null,"color":null,"v180":null,"talla2":null,"talla_usa":null,"talla_uk":null,"talla_jp":null,"stock_reservat":0,"v90":null,"desc_brand":"0.00","exist":0,"rec":"355.71","pmp":"186.00","v30":null,"id_producte":"18168347","baja":"0","referencia":"1360065","sellers":[]}],"familias":null,"video_mp4":0,"fecha_descatalogado":"2078-12-31T00:00:00","image_created":null,"tres_sesenta":"0","precio_win":221.99,"id_pos_producte_win":0,"id_marca":"2947","precio_tachado":0,"list_atributos":""},{"id_modelo":"140227054","nombre_modelo":"90 Lite 5G 8GB\/256GB 6.7\u00b4\u00b4 Dual Sim","nombre_modelo_eng":"90 Lite 5G 8GB\/256GB 6.7\u00b4\u00b4 Dual Sim","marca":"Honor","sostenible":0,"productes":[{"brut":"187.95","v360":null,"talla":null,"color":null,"v180":null,"talla2":null,"talla_usa":null,"talla_uk":null,"talla_jp":null,"stock_reservat":0,"v90":null,"desc_brand":"0.00","exist":0,"rec":"363.36","pmp":"187.95","v30":null,"id_producte":"140821092","baja":"0","referencia":"5109ASWC","sellers":[]}],"familias":null,"video_mp4":0,"fecha_descatalogado":"2078-12-31T00:00:00","image_created":null,"tres_sesenta":"0","precio_win":223.99,"id_pos_producte_win":0,"id_marca":"4341","precio_tachado":0,"list_atributos":""},{"id_modelo":"139358833","nombre_modelo":"Edge 20 Lite 8\/128GB 6.7\u00b4\u00b4 Dual Sim","nombre_modelo_eng":"Edge 20 Lite 8\/128GB 6.7\u00b4\u00b4 Dual Sim","marca":"Motorola","sostenible":0,"productes":[{"brut":"187.24","v360":null,"talla":null,"color":null,"v180":null,"talla2":null,"talla_usa":null,"talla_uk":null,"talla_jp":null,"stock_reservat":0,"v90":null,"desc_brand":"0.00","exist":0,"rec":"376.23","pmp":"187.24","v30":null,"id_producte":"17772472","baja":"0","referencia":"PANE0044PL","sellers":[]}],"familias":null,"video_mp4":0,"fecha_descatalogado":"2078-12-31T00:00:00","image_created":null,"tres_sesenta":"0","precio_win":224.49,"id_pos_producte_win":0,"id_marca":"2180","precio_tachado":0,"list_atributos":""},{"id_modelo":"139546259","nombre_modelo":"Galaxy A23 5G 4GB\/64GB 6.6\u00b4\u00b4 Dual Sim","nombre_modelo_eng":"Galaxy A23 5G 4GB\/64GB 6.6\u00b4\u00b4 Dual Sim","marca":"Samsung","sostenible":0,"productes":[{"brut":"187.00","v360":null,"talla":null,"color":null,"v180":null,"talla2":null,"talla_usa":null,"talla_uk":null,"talla_jp":null,"stock_reservat":0,"v90":null,"desc_brand":"0.00","exist":0,"rec":"382.01","pmp":"187.00","v30":null,"id_producte":"18489269","baja":"0","referencia":"128129","sellers":[]}],"familias":null,"video_mp4":0,"fecha_descatalogado":"2078-12-31T00:00:00","image_created":null,"tres_sesenta":"0","precio_win":224.99,"id_pos_producte_win":0,"id_marca":"2947","precio_tachado":0,"list_atributos":""},{"id_modelo":"140293544","nombre_modelo":"Redmi Note 12 Pro 8GB\/256GB 6.67\u00b4\u00b4 Dual Sim","nombre_modelo_eng":"Redmi Note 12 Pro 8GB\/256GB 6.67\u00b4\u00b4 Dual Sim","marca":"Xiaomi","sostenible":0,"productes":[{"brut":"193.87","v360":null,"talla":null,"color":null,"v180":null,"talla2":null,"talla_usa":null,"talla_uk":null,"talla_jp":null,"stock_reservat":0,"v90":null,"desc_brand":"0.00","exist":0,"rec":"292.92","pmp":"193.87","v30":null,"id_producte":"141066133","baja":"0","referencia":"MZB0DFBEU","sellers":[]}],"familias":null,"video_mp4":0,"fecha_descatalogado":"2078-12-31T00:00:00","image_created":null,"tres_sesenta":"0","precio_win":225.49,"id_pos_producte_win":0,"id_marca":"2696","precio_tachado":0,"list_atributos":""},{"id_modelo":"139117570","nombre_modelo":"8100 Plus 2GB\/32GB 6.1\u00b4\u00b4","nombre_modelo_eng":"8100 Plus 2GB\/32GB 6.1\u00b4\u00b4","marca":"Doro","sostenible":0,"productes":[{"brut":"193.95","v360":null,"talla":null,"color":null,"v180":null,"talla2":null,"talla_usa":null,"talla_uk":null,"talla_jp":null,"stock_reservat":0,"v90":null,"desc_brand":"0.00","exist":3,"rec":"300.00","pmp":"193.95","v30":null,"id_producte":"16951786","baja":"0","referencia":"380501","sellers":[]}],"familias":null,"video_mp4":0,"fecha_descatalogado":"2078-12-31T00:00:00","image_created":null,"tres_sesenta":"1","precio_win":225.99,"id_pos_producte_win":0,"id_marca":"5338","precio_tachado":0,"list_atributos":""},{"id_modelo":"140293545","nombre_modelo":"Redmi Note 12 Pro 8GB\/256GB 6.67\u00b4\u00b4 Dual Sim","nombre_modelo_eng":"Redmi Note 12 Pro 8GB\/256GB 6.67\u00b4\u00b4 Dual Sim","marca":"Xiaomi","sostenible":0,"productes":[{"brut":"195.74","v360":null,"talla":null,"color":null,"v180":null,"talla2":null,"talla_usa":null,"talla_uk":null,"talla_jp":null,"stock_reservat":2,"v90":null,"desc_brand":"0.00","exist":1,"rec":"292.92","pmp":"193.61","v30":null,"id_producte":"141066134","baja":"0","referencia":"MZB0DEHEU","sellers":[]}],"familias":null,"video_mp4":0,"fecha_descatalogado":"2078-12-31T00:00:00","image_created":null,"tres_sesenta":"0","precio_win":227.49,"id_pos_producte_win":0,"id_marca":"2696","precio_tachado":0,"list_atributos":""},{"id_modelo":"140392798","nombre_modelo":"A78 4G 8GB\/128GB 6.4\u00b4\u00b4","nombre_modelo_eng":"A78 4G 8GB\/128GB 6.4\u00b4\u00b4","marca":"Oppo","sostenible":0,"productes":[{"brut":"183.24","v360":null,"talla":null,"color":null,"v180":null,"talla2":null,"talla_usa":null,"talla_uk":null,"talla_jp":null,"stock_reservat":0,"v90":null,"desc_brand":"0.00","exist":0,"rec":"286.92","pmp":"183.24","v30":null,"id_producte":"141353960","baja":"0","referencia":"631010000067","sellers":[]}],"familias":null,"video_mp4":0,"fecha_descatalogado":"2078-12-31T00:00:00","image_created":null,"tres_sesenta":"0","precio_win":227.99,"id_pos_producte_win":0,"id_marca":"4981","precio_tachado":0,"list_atributos":""},{"id_modelo":"139899811","nombre_modelo":"Redmi Note 12 Pro 8GB\/256GB 6.67\u00b4\u00b4 Dual Sim","nombre_modelo_eng":"Redmi Note 12 Pro 8GB\/256GB 6.67\u00b4\u00b4 Dual Sim","marca":"Xiaomi","sostenible":0,"productes":[{"brut":"194.28","v360":null,"talla":null,"color":null,"v180":null,"talla2":null,"talla_usa":null,"talla_uk":null,"talla_jp":null,"stock_reservat":2,"v90":null,"desc_brand":"0.00","exist":1,"rec":"329.34","pmp":"189.95","v30":null,"id_producte":"19885957","baja":"0","referencia":"NOTE12P 4G 8-256 BK","sellers":[]}],"familias":null,"video_mp4":0,"fecha_descatalogado":"2078-12-31T00:00:00","image_created":null,"tres_sesenta":"0","precio_win":228.49,"id_pos_producte_win":0,"id_marca":"2696","precio_tachado":0,"list_atributos":""},{"id_modelo":"138068661","nombre_modelo":"Mi 10T Lite 5G 6GB\/128GB 6.67\u00b4\u00b4 Dual SIM","nombre_modelo_eng":"Mi 10T Lite 5G 6GB\/128GB 6.67\u00b4\u00b4 Dual SIM","marca":"Xiaomi","sostenible":0,"productes":[{"brut":"192.15","v360":null,"talla":null,"color":null,"v180":null,"talla2":null,"talla_usa":null,"talla_uk":null,"talla_jp":null,"stock_reservat":0,"v90":null,"desc_brand":"0.00","exist":0,"rec":"361.81","pmp":"192.15","v30":null,"id_producte":"12962282","baja":"0","referencia":"MZB07XEEU","sellers":[]}],"familias":null,"video_mp4":0,"fecha_descatalogado":"2078-12-31T00:00:00","image_created":null,"tres_sesenta":"1","precio_win":228.99,"id_pos_producte_win":0,"id_marca":"2696","precio_tachado":0,"list_atributos":""},{"id_modelo":"138232108","nombre_modelo":"S42 H+","nombre_modelo_eng":"S42 H+","marca":"Cat","sostenible":0,"productes":[{"brut":"169.00","v360":null,"talla":null,"color":null,"v180":null,"talla2":null,"talla_usa":null,"talla_uk":null,"talla_jp":null,"stock_reservat":0,"v90":null,"desc_brand":"0.00","exist":0,"rec":"553.07","pmp":"169.00","v30":null,"id_producte":"13719115","baja":"0","referencia":"CS42H-DAB-RON-NN","sellers":[]}],"familias":null,"video_mp4":0,"fecha_descatalogado":"2078-12-31T00:00:00","image_created":null,"tres_sesenta":"1","precio_win":230.99,"id_pos_producte_win":0,"id_marca":"3923","precio_tachado":0,"list_atributos":""},{"id_modelo":"139733283","nombre_modelo":"8100 2GB\/128GB 6.1\u00b4\u00b4 Dual Sim + Smarwatch","nombre_modelo_eng":"8100 2GB\/128GB 6.1\u00b4\u00b4 Dual Sim + Smarwatch","marca":"Doro","sostenible":0,"productes":[{"brut":"201.65","v360":null,"talla":null,"color":null,"v180":null,"talla2":null,"talla_usa":null,"talla_uk":null,"talla_jp":null,"stock_reservat":0,"v90":null,"desc_brand":"0.00","exist":0,"rec":"320.36","pmp":"201.65","v30":null,"id_producte":"19289492","baja":"0","referencia":"DSP0000013614","sellers":[]}],"familias":null,"video_mp4":0,"fecha_descatalogado":"2078-12-31T00:00:00","image_created":null,"tres_sesenta":"0","precio_win":235.99,"id_pos_producte_win":0,"id_marca":"5338","precio_tachado":0,"list_atributos":""},{"id_modelo":"139861455","nombre_modelo":"Redmi Note 12 5G 6GB\/128GB 6.67\u00b4\u00b4 Dual Sim","nombre_modelo_eng":"Redmi Note 12 5G 6GB\/128GB 6.67\u00b4\u00b4 Dual Sim","marca":"Xiaomi","sostenible":0,"productes":[{"brut":"192.57","v360":null,"talla":null,"color":null,"v180":null,"talla2":null,"talla_usa":null,"talla_uk":null,"talla_jp":null,"stock_reservat":0,"v90":null,"desc_brand":"0.00","exist":0,"rec":"453.09","pmp":"192.57","v30":null,"id_producte":"19725320","baja":"0","referencia":"MZB0CY4EU","sellers":[]}],"familias":null,"video_mp4":0,"fecha_descatalogado":"2078-12-31T00:00:00","image_created":null,"tres_sesenta":"1","precio_win":235.99,"id_pos_producte_win":0,"id_marca":"2696","precio_tachado":0,"list_atributos":""},{"id_modelo":"139733282","nombre_modelo":"8100 2GB\/128GB 6.1\u00b4\u00b4 Dual Sim + Smarwatch","nombre_modelo_eng":"8100 2GB\/128GB 6.1\u00b4\u00b4 Dual Sim + Smarwatch","marca":"Doro","sostenible":0,"productes":[{"brut":"201.65","v360":null,"talla":null,"color":null,"v180":null,"talla2":null,"talla_usa":null,"talla_uk":null,"talla_jp":null,"stock_reservat":0,"v90":null,"desc_brand":"0.00","exist":0,"rec":"320.36","pmp":"201.65","v30":null,"id_producte":"19289491","baja":"0","referencia":"DSP0000013613","sellers":[]}],"familias":null,"video_mp4":0,"fecha_descatalogado":"2078-12-31T00:00:00","image_created":null,"tres_sesenta":"0","precio_win":235.99,"id_pos_producte_win":0,"id_marca":"5338","precio_tachado":0,"list_atributos":""},{"id_modelo":"139899808","nombre_modelo":"Redmi Note 12 Pro 5G 6GB\/128GB 6.67\u00b4\u00b4 Dual Sim","nombre_modelo_eng":"Redmi Note 12 Pro 5G 6GB\/128GB 6.67\u00b4\u00b4 Dual Sim","marca":"Xiaomi","sostenible":0,"productes":[{"brut":"199.70","v360":null,"talla":null,"color":null,"v180":null,"talla2":null,"talla_usa":null,"talla_uk":null,"talla_jp":null,"stock_reservat":0,"v90":null,"desc_brand":"0.00","exist":0,"rec":"360.21","pmp":"199.70","v30":null,"id_producte":"19885954","baja":"0","referencia":"NOTE12P 6-128 BK","sellers":[]}],"familias":null,"video_mp4":0,"fecha_descatalogado":"2078-12-31T00:00:00","image_created":null,"tres_sesenta":"0","precio_win":236.49,"id_pos_producte_win":0,"id_marca":"2696","precio_tachado":0,"list_atributos":""},{"id_modelo":"139431041","nombre_modelo":"Caterpillar S42H+ 3\/32GB 5.5\u00b4\u00b4 Dual Sim","nombre_modelo_eng":"Caterpillar S42H+ 3\/32GB 5.5\u00b4\u00b4 Dual Sim","marca":"Bullit","sostenible":0,"productes":[{"brut":"176.47","v360":null,"talla":null,"color":null,"v180":null,"talla2":null,"talla_usa":null,"talla_uk":null,"talla_jp":null,"stock_reservat":0,"v90":null,"desc_brand":"0.00","exist":0,"rec":"419.52","pmp":"176.47","v30":null,"id_producte":"17986810","baja":"0","referencia":"CE67652","sellers":[]}],"familias":null,"video_mp4":0,"fecha_descatalogado":"2078-12-31T00:00:00","image_created":null,"tres_sesenta":"0","precio_win":236.49,"id_pos_producte_win":0,"id_marca":"12363","precio_tachado":0,"list_atributos":""},{"id_modelo":"140333472","nombre_modelo":"Reno 8T 8GB\/128GB 6.43\u00b4\u00b4 Dual Sim","nombre_modelo_eng":"Reno 8T 8GB\/128GB 6.43\u00b4\u00b4 Dual Sim","marca":"Oppo","sostenible":0,"productes":[{"brut":"190.79","v360":null,"talla":null,"color":null,"v180":null,"talla2":null,"talla_usa":null,"talla_uk":null,"talla_jp":null,"stock_reservat":0,"v90":null,"desc_brand":"0.00","exist":0,"rec":"298.09","pmp":"190.79","v30":null,"id_producte":"141160461","baja":"0","referencia":"CPH2481O","sellers":[]}],"familias":null,"video_mp4":0,"fecha_descatalogado":"2078-12-31T00:00:00","image_created":null,"tres_sesenta":"0","precio_win":236.99,"id_pos_producte_win":0,"id_marca":"4981","precio_tachado":0,"list_atributos":""},{"id_modelo":"140333471","nombre_modelo":"Reno 8T 8GB\/128GB 6.43\u00b4\u00b4 Dual Sim","nombre_modelo_eng":"Reno 8T 8GB\/128GB 6.43\u00b4\u00b4 Dual Sim","marca":"Oppo","sostenible":0,"productes":[{"brut":"190.79","v360":null,"talla":null,"color":null,"v180":null,"talla2":null,"talla_usa":null,"talla_uk":null,"talla_jp":null,"stock_reservat":0,"v90":null,"desc_brand":"0.00","exist":0,"rec":"298.06","pmp":"190.79","v30":null,"id_producte":"141160460","baja":"0","referencia":"CPH2481","sellers":[]}],"familias":null,"video_mp4":0,"fecha_descatalogado":"2078-12-31T00:00:00","image_created":null,"tres_sesenta":"0","precio_win":236.99,"id_pos_producte_win":0,"id_marca":"4981","precio_tachado":0,"list_atributos":""},{"id_modelo":"139859817","nombre_modelo":"A78 5G 8GB\/128GB 6.7\u00b4\u00b4 Dual Sim","nombre_modelo_eng":"A78 5G 8GB\/128GB 6.7\u00b4\u00b4 Dual Sim","marca":"Oppo","sostenible":0,"productes":[{"brut":"186.50","v360":null,"talla":null,"color":null,"v180":null,"talla2":null,"talla_usa":null,"talla_uk":null,"talla_jp":null,"stock_reservat":0,"v90":null,"desc_brand":"0.00","exist":0,"rec":"351.80","pmp":"186.50","v30":null,"id_producte":"19720542","baja":"0","referencia":"6054391","sellers":[]}],"familias":null,"video_mp4":0,"fecha_descatalogado":"2078-12-31T00:00:00","image_created":null,"tres_sesenta":"0","precio_win":238.99,"id_pos_producte_win":0,"id_marca":"4981","precio_tachado":0,"list_atributos":""},{"id_modelo":"139594772","nombre_modelo":"Galaxy M23 5G 4GB\/128GB 6.6\u00b4\u00b4 Dual Sim","nombre_modelo_eng":"Galaxy M23 5G 4GB\/128GB 6.6\u00b4\u00b4 Dual Sim","marca":"Samsung","sostenible":0,"productes":[{"brut":"209.72","v360":null,"talla":null,"color":null,"v180":null,"talla2":null,"talla_usa":null,"talla_uk":null,"talla_jp":null,"stock_reservat":0,"v90":null,"desc_brand":"0.00","exist":0,"rec":"262.56","pmp":"209.72","v30":null,"id_producte":"18732610","baja":"0","referencia":"TKOSA1SZA0994","sellers":[]}],"familias":null,"video_mp4":0,"fecha_descatalogado":"2078-12-31T00:00:00","image_created":null,"tres_sesenta":"0","precio_win":239.99,"id_pos_producte_win":0,"id_marca":"2947","precio_tachado":0,"list_atributos":""},{"id_modelo":"139859818","nombre_modelo":"A78 5G 8GB\/128GB 6.7\u00b4\u00b4 Dual Sim","nombre_modelo_eng":"A78 5G 8GB\/128GB 6.7\u00b4\u00b4 Dual Sim","marca":"Oppo","sostenible":0,"productes":[{"brut":"192.97","v360":null,"talla":null,"color":null,"v180":null,"talla2":null,"talla_usa":null,"talla_uk":null,"talla_jp":null,"stock_reservat":0,"v90":null,"desc_brand":"0.00","exist":0,"rec":"338.89","pmp":"192.97","v30":null,"id_producte":"19720543","baja":"0","referencia":"6054670","sellers":[]}],"familias":null,"video_mp4":0,"fecha_descatalogado":"2078-12-31T00:00:00","image_created":null,"tres_sesenta":"0","precio_win":243.99,"id_pos_producte_win":0,"id_marca":"4981","precio_tachado":0,"list_atributos":""},{"id_modelo":"137355403","nombre_modelo":"GX290 3GB\/32GB 6.1\u00b4\u00b4 Dual SIM","nombre_modelo_eng":"GX290 3GB\/32GB 6.1\u00b4\u00b4 Dual SIM","marca":"Gigaset","sostenible":0,"productes":[{"brut":"209.50","v360":null,"talla":null,"color":null,"v180":null,"talla2":null,"talla_usa":null,"talla_uk":null,"talla_jp":null,"stock_reservat":0,"v90":null,"desc_brand":"0.00","exist":0,"rec":"325.52","pmp":"209.50","v30":null,"id_producte":"9673343","baja":"0","referencia":"S30853-H1516-R101","sellers":[]}],"familias":null,"video_mp4":0,"fecha_descatalogado":"2078-12-31T00:00:00","image_created":null,"tres_sesenta":"1","precio_win":243.99,"id_pos_producte_win":0,"id_marca":"4347","precio_tachado":0,"list_atributos":""},{"id_modelo":"138999976","nombre_modelo":"V21 5G (V2050) 8GB\/128GB 6.5\u00b4\u00b4 Dual Sim","nombre_modelo_eng":"V21 5G (V2050) 8GB\/128GB 6.5\u00b4\u00b4 Dual Sim","marca":"Vivo","sostenible":0,"productes":[{"brut":"169.16","v360":null,"talla":null,"color":null,"v180":null,"talla2":null,"talla_usa":null,"talla_uk":null,"talla_jp":null,"stock_reservat":1,"v90":null,"desc_brand":"0.00","exist":0,"rec":"566.00","pmp":"169.16","v30":null,"id_producte":"16450397","baja":"0","referencia":"40-48-6087","sellers":[]}],"familias":null,"video_mp4":0,"fecha_descatalogado":"2078-12-31T00:00:00","image_created":null,"tres_sesenta":"0","precio_win":245.99,"id_pos_producte_win":0,"id_marca":"5560","precio_tachado":0,"list_atributos":""},{"id_modelo":"139693346","nombre_modelo":"Redmi Note 11 Pro 5G 6GB\/128GB 6.7\u00b4\u00b4 Dual Sim","nombre_modelo_eng":"Redmi Note 11 Pro 5G 6GB\/128GB 6.7\u00b4\u00b4 Dual Sim","marca":"Xiaomi","sostenible":0,"productes":[{"brut":"179.70","v360":null,"talla":null,"color":null,"v180":null,"talla2":null,"talla_usa":null,"talla_uk":null,"talla_jp":null,"stock_reservat":0,"v90":null,"desc_brand":"0.00","exist":1,"rec":"384.12","pmp":"207.30","v30":null,"id_producte":"19126195","baja":"0","referencia":"MZB0AW3EU","sellers":[]}],"familias":null,"video_mp4":0,"fecha_descatalogado":"2078-12-31T00:00:00","image_created":null,"tres_sesenta":"0","precio_win":245.99,"id_pos_producte_win":0,"id_marca":"2696","precio_tachado":0,"list_atributos":""},{"id_modelo":"139776816","nombre_modelo":"Magic 5 Lite 5G 6GB\/128GB 6.8\u00b4\u00b4 Dual Sim","nombre_modelo_eng":"Magic 5 Lite 5G 6GB\/128GB 6.8\u00b4\u00b4 Dual Sim","marca":"Honor","sostenible":0,"productes":[{"brut":"189.70","v360":null,"talla":null,"color":null,"v180":null,"talla2":null,"talla_usa":null,"talla_uk":null,"talla_jp":null,"stock_reservat":0,"v90":null,"desc_brand":"0.00","exist":1,"rec":"429.85","pmp":"204.75","v30":null,"id_producte":"19473258","baja":"0","referencia":"5109AMAA","sellers":[]}],"familias":null,"video_mp4":0,"fecha_descatalogado":"2078-12-31T00:00:00","image_created":null,"tres_sesenta":"0","precio_win":246.99,"id_pos_producte_win":0,"id_marca":"4341","precio_tachado":0,"list_atributos":""},{"id_modelo":"139899807","nombre_modelo":"Redmi Note 12 Pro 5G 6GB\/128GB 6.67\u00b4\u00b4 Dual Sim","nombre_modelo_eng":"Redmi Note 12 Pro 5G 6GB\/128GB 6.67\u00b4\u00b4 Dual Sim","marca":"Xiaomi","sostenible":0,"productes":[{"brut":"210.37","v360":null,"talla":null,"color":null,"v180":null,"talla2":null,"talla_usa":null,"talla_uk":null,"talla_jp":null,"stock_reservat":0,"v90":null,"desc_brand":"0.00","exist":0,"rec":"360.21","pmp":"210.37","v30":null,"id_producte":"19885953","baja":"0","referencia":"NOTE12P 6-128 BL","sellers":[]}],"familias":null,"video_mp4":0,"fecha_descatalogado":"2078-12-31T00:00:00","image_created":null,"tres_sesenta":"0","precio_win":247.99,"id_pos_producte_win":0,"id_marca":"2696","precio_tachado":0,"list_atributos":""},{"id_modelo":"139457993","nombre_modelo":"Galaxy A23 5G 4GB\/128GB 6.6\u00b4\u00b4 Dual Sim","nombre_modelo_eng":"Galaxy A23 5G 4GB\/128GB 6.6\u00b4\u00b4 Dual Sim","marca":"Samsung","sostenible":0,"productes":[{"brut":"175.87","v360":null,"talla":null,"color":null,"v180":null,"talla2":null,"talla_usa":null,"talla_uk":null,"talla_jp":null,"stock_reservat":0,"v90":null,"desc_brand":"0.00","exist":1,"rec":"414.74","pmp":"208.00","v30":null,"id_producte":"18138232","baja":"0","referencia":"SM_A236BLBVEUB","sellers":[]}],"familias":null,"video_mp4":0,"fecha_descatalogado":"2078-12-31T00:00:00","image_created":null,"tres_sesenta":"1","precio_win":248.99,"id_pos_producte_win":0,"id_marca":"2947","precio_tachado":0,"list_atributos":""},{"id_modelo":"139889116","nombre_modelo":"Mi11 Lite 5G NE 6GB\/128GB 6.55\u00b4\u00b4 Dual Sim Refurbished","nombre_modelo_eng":"Mi11 Lite 5G NE 6GB\/128GB 6.55\u00b4\u00b4 Dual Sim Refurbished","marca":"Xiaomi","sostenible":0,"productes":[{"brut":"154.95","v360":null,"talla":null,"color":null,"v180":null,"talla2":null,"talla_usa":null,"talla_uk":null,"talla_jp":null,"stock_reservat":0,"v90":null,"desc_brand":"0.00","exist":0,"rec":"284.85","pmp":"154.95","v30":null,"id_producte":"19823548","baja":"0","referencia":"RFXMI11L5NE128B","sellers":[]}],"familias":null,"video_mp4":0,"fecha_descatalogado":"2078-12-31T00:00:00","image_created":null,"tres_sesenta":"0","precio_win":248.99,"id_pos_producte_win":0,"id_marca":"2696","precio_tachado":0,"list_atributos":""},{"id_modelo":"139632739","nombre_modelo":"Reno 7 Lite 8GB\/128GB 6.4\u00b4\u00b4 Dual Sim","nombre_modelo_eng":"Reno 7 Lite 8GB\/128GB 6.4\u00b4\u00b4 Dual Sim","marca":"Oppo","sostenible":0,"productes":[{"brut":"173.39","v360":null,"talla":null,"color":null,"v180":null,"talla2":null,"talla_usa":null,"talla_uk":null,"talla_jp":null,"stock_reservat":0,"v90":null,"desc_brand":"0.00","exist":1,"rec":"369.85","pmp":"194.42","v30":null,"id_producte":"18898146","baja":"0","referencia":"TKOOPPSZA0018","sellers":[]}],"familias":null,"video_mp4":0,"fecha_descatalogado":"2078-12-31T00:00:00","image_created":null,"tres_sesenta":"1","precio_win":248.99,"id_pos_producte_win":0,"id_marca":"4981","precio_tachado":0,"list_atributos":""},{"id_modelo":"137689888","nombre_modelo":"Core T4 3GB\/32GB 8\u00b4\u00b4","nombre_modelo_eng":"Core T4 3GB\/32GB 8\u00b4\u00b4","marca":"Crosscall","sostenible":0,"productes":[{"brut":"197.83","v360":null,"talla":null,"color":null,"v180":null,"talla2":null,"talla_usa":null,"talla_uk":null,"talla_jp":null,"stock_reservat":0,"v90":null,"desc_brand":"0.00","exist":0,"rec":"574.32","pmp":"197.83","v30":null,"id_producte":"11381214","baja":"0","referencia":"COT4.TAB.OPM","sellers":[]}],"familias":null,"video_mp4":0,"fecha_descatalogado":"2078-12-31T00:00:00","image_created":null,"tres_sesenta":"0","precio_win":249.99,"id_pos_producte_win":0,"id_marca":"4401","precio_tachado":0,"list_atributos":""},{"id_modelo":"140383136","nombre_modelo":"Magic 5 Lite 5G 8GB\/256GB 6.7\u00b4\u00b4 Dual Sim","nombre_modelo_eng":"Magic 5 Lite 5G 8GB\/256GB 6.7\u00b4\u00b4 Dual Sim","marca":"Honor","sostenible":0,"productes":[{"brut":"206.70","v360":null,"talla":null,"color":null,"v180":null,"talla2":null,"talla_usa":null,"talla_uk":null,"talla_jp":null,"stock_reservat":0,"v90":null,"desc_brand":"0.00","exist":0,"rec":"462.63","pmp":"206.70","v30":null,"id_producte":"141322045","baja":"0","referencia":"5109ARUL","sellers":[]}],"familias":null,"video_mp4":0,"fecha_descatalogado":"2078-12-31T00:00:00","image_created":null,"tres_sesenta":"0","precio_win":250.99,"id_pos_producte_win":0,"id_marca":"4341","precio_tachado":0,"list_atributos":""},{"id_modelo":"139131171","nombre_modelo":"Galaxy A33 5G Enterprise Edition 6GB\/128GB 6.4\u00b4\u00b4 Dual Sim","nombre_modelo_eng":"Galaxy A33 5G Enterprise Edition 6GB\/128GB 6.4\u00b4\u00b4 Dual Sim","marca":"Samsung","sostenible":0,"productes":[{"brut":"209.97","v360":null,"talla":null,"color":null,"v180":null,"talla2":null,"talla_usa":null,"talla_uk":null,"talla_jp":null,"stock_reservat":0,"v90":null,"desc_brand":"0.00","exist":0,"rec":"454.43","pmp":"209.97","v30":null,"id_producte":"17003676","baja":"0","referencia":"SM-A336BZKGEEB","sellers":[]}],"familias":null,"video_mp4":0,"fecha_descatalogado":"2078-12-31T00:00:00","image_created":null,"tres_sesenta":"0","precio_win":253.99,"id_pos_producte_win":0,"id_marca":"2947","precio_tachado":0,"list_atributos":""},{"id_modelo":"139632733","nombre_modelo":"Moto G72 8GB\/128GB 6.6\u00b4\u00b4 Dual Sim","nombre_modelo_eng":"Moto G72 8GB\/128GB 6.6\u00b4\u00b4 Dual Sim","marca":"Motorola","sostenible":0,"productes":[{"brut":"157.92","v360":null,"talla":null,"color":null,"v180":null,"talla2":null,"talla_usa":null,"talla_uk":null,"talla_jp":null,"stock_reservat":0,"v90":null,"desc_brand":"0.00","exist":1,"rec":"359.72","pmp":"216.56","v30":null,"id_producte":"18898140","baja":"0","referencia":"TKOMOTSZA0169","sellers":[]}],"familias":null,"video_mp4":0,"fecha_descatalogado":"2078-12-31T00:00:00","image_created":null,"tres_sesenta":"1","precio_win":253.99,"id_pos_producte_win":0,"id_marca":"2180","precio_tachado":0,"list_atributos":""},{"id_modelo":"140333463","nombre_modelo":"Nord Ce 3 Lite 5G 8GB\/128GB 6.7\u00b4\u00b4 Dual Sim","nombre_modelo_eng":"Nord Ce 3 Lite 5G 8GB\/128GB 6.7\u00b4\u00b4 Dual Sim","marca":"Oneplus","sostenible":0,"productes":[{"brut":"205.81","v360":null,"talla":null,"color":null,"v180":null,"talla2":null,"talla_usa":null,"talla_uk":null,"talla_jp":null,"stock_reservat":0,"v90":null,"desc_brand":"0.00","exist":0,"rec":"314.17","pmp":"205.81","v30":null,"id_producte":"141160452","baja":"0","referencia":"CPH2465","sellers":[]}],"familias":null,"video_mp4":0,"fecha_descatalogado":"2078-12-31T00:00:00","image_created":null,"tres_sesenta":"0","precio_win":254.99,"id_pos_producte_win":0,"id_marca":"6169","precio_tachado":0,"list_atributos":""},{"id_modelo":"139570565","nombre_modelo":"Edge 30 Neo 5G 8GB\/128GB 6.3\u00b4\u00b4 Dual Sim","nombre_modelo_eng":"Edge 30 Neo 5G 8GB\/128GB 6.3\u00b4\u00b4 Dual Sim","marca":"Motorola","sostenible":0,"productes":[{"brut":"208.66","v360":null,"talla":null,"color":null,"v180":null,"talla2":null,"talla_usa":null,"talla_uk":null,"talla_jp":null,"stock_reservat":1,"v90":null,"desc_brand":"0.00","exist":0,"rec":"501.80","pmp":"208.66","v30":null,"id_producte":"18607690","baja":"0","referencia":"PAV00000SE","sellers":[]}],"familias":null,"video_mp4":0,"fecha_descatalogado":"2078-12-31T00:00:00","image_created":null,"tres_sesenta":"0","precio_win":255.99,"id_pos_producte_win":0,"id_marca":"2180","precio_tachado":0,"list_atributos":""},{"id_modelo":"140333469","nombre_modelo":"Reno 6 5G 8GB\/128GB 6.7\u00b4\u00b4 Dual Sim","nombre_modelo_eng":"Reno 6 5G 8GB\/128GB 6.7\u00b4\u00b4 Dual Sim","marca":"Oppo","sostenible":0,"productes":[{"brut":"205.63","v360":null,"talla":null,"color":null,"v180":null,"talla2":null,"talla_usa":null,"talla_uk":null,"talla_jp":null,"stock_reservat":0,"v90":null,"desc_brand":"0.00","exist":0,"rec":"330.30","pmp":"205.63","v30":null,"id_producte":"141160458","baja":"0","referencia":"CPH2251","sellers":[]}],"familias":null,"video_mp4":0,"fecha_descatalogado":"2078-12-31T00:00:00","image_created":null,"tres_sesenta":"0","precio_win":256.49,"id_pos_producte_win":0,"id_marca":"4981","precio_tachado":0,"list_atributos":""},{"id_modelo":"139693347","nombre_modelo":"Redmi Note 11 Pro 5G 6GB\/128GB 6.7\u00b4\u00b4 Dual Sim","nombre_modelo_eng":"Redmi Note 11 Pro 5G 6GB\/128GB 6.7\u00b4\u00b4 Dual Sim","marca":"Xiaomi","sostenible":0,"productes":[{"brut":"179.20","v360":null,"talla":null,"color":null,"v180":null,"talla2":null,"talla_usa":null,"talla_uk":null,"talla_jp":null,"stock_reservat":0,"v90":null,"desc_brand":"0.00","exist":2,"rec":"384.12","pmp":"217.48","v30":null,"id_producte":"19126196","baja":"0","referencia":"MZB0AUCEU","sellers":[]}],"familias":null,"video_mp4":0,"fecha_descatalogado":"2078-12-31T00:00:00","image_created":null,"tres_sesenta":"1","precio_win":256.99,"id_pos_producte_win":0,"id_marca":"2696","precio_tachado":0,"list_atributos":""},{"id_modelo":"138999980","nombre_modelo":"Mi 11 Lite 5G NE 8gb\/128gb 6.6\u00b4\u00b4 Dual Sim","nombre_modelo_eng":"Mi 11 Lite 5G NE 8gb\/128gb 6.6\u00b4\u00b4 Dual Sim","marca":"Xiaomi","sostenible":0,"productes":[{"brut":"219.70","v360":null,"talla":null,"color":null,"v180":null,"talla2":null,"talla_usa":null,"talla_uk":null,"talla_jp":null,"stock_reservat":0,"v90":null,"desc_brand":"0.00","exist":0,"rec":"399.90","pmp":"219.70","v30":null,"id_producte":"16450401","baja":"0","referencia":"MZB08JZEU","sellers":[]}],"familias":null,"video_mp4":0,"fecha_descatalogado":"2078-12-31T00:00:00","image_created":null,"tres_sesenta":"0","precio_win":260,"id_pos_producte_win":0,"id_marca":"2696","precio_tachado":0,"list_atributos":""},{"id_modelo":"139889075","nombre_modelo":"iPhone XR 64GB 6.1\u00b4\u00b4 Dual Sim Refurbished AB","nombre_modelo_eng":"iPhone XR 64GB 6.1\u00b4\u00b4 Dual Sim Refurbished AB","marca":"Apple","sostenible":0,"productes":[{"brut":"219.95","v360":null,"talla":null,"color":null,"v180":null,"talla2":null,"talla_usa":null,"talla_uk":null,"talla_jp":null,"stock_reservat":0,"v90":null,"desc_brand":"0.00","exist":0,"rec":"349.52","pmp":"219.95","v30":null,"id_producte":"19823507","baja":"0","referencia":"SLIPXR64BLKAB","sellers":[]}],"familias":null,"video_mp4":0,"fecha_descatalogado":"2078-12-31T00:00:00","image_created":null,"tres_sesenta":"0","precio_win":261.49,"id_pos_producte_win":0,"id_marca":"4321","precio_tachado":0,"list_atributos":""},{"id_modelo":"139899801","nombre_modelo":"POCO X5 5G 8GB\/256GB 6.67\u00b4\u00b4 Dual Sim","nombre_modelo_eng":"POCO X5 5G 8GB\/256GB 6.67\u00b4\u00b4 Dual Sim","marca":"Xiaomi","sostenible":0,"productes":[{"brut":"208.95","v360":null,"talla":null,"color":null,"v180":null,"talla2":null,"talla_usa":null,"talla_uk":null,"talla_jp":null,"stock_reservat":0,"v90":null,"desc_brand":"0.00","exist":1,"rec":"357.84","pmp":"223.88","v30":null,"id_producte":"19885947","baja":"0","referencia":"POCO X5 5G 8-256 BK","sellers":[]}],"familias":null,"video_mp4":0,"fecha_descatalogado":"2078-12-31T00:00:00","image_created":null,"tres_sesenta":"0","precio_win":261.99,"id_pos_producte_win":0,"id_marca":"2696","precio_tachado":0,"list_atributos":""},{"id_modelo":"139562234","nombre_modelo":"Armor 15 6GB\/128GB 5.5\u00b4\u00b4 Dual Sim","nombre_modelo_eng":"Armor 15 6GB\/128GB 5.5\u00b4\u00b4 Dual Sim","marca":"Ulefone","sostenible":0,"productes":[{"brut":"203.36","v360":null,"talla":null,"color":null,"v180":null,"talla2":null,"talla_usa":null,"talla_uk":null,"talla_jp":null,"stock_reservat":0,"v90":null,"desc_brand":"0.00","exist":0,"rec":"394.38","pmp":"203.36","v30":null,"id_producte":"18575483","baja":"0","referencia":"1362020","sellers":[]}],"familias":null,"video_mp4":0,"fecha_descatalogado":"2078-12-31T00:00:00","image_created":null,"tres_sesenta":"0","precio_win":261.99,"id_pos_producte_win":0,"id_marca":"6373","precio_tachado":0,"list_atributos":""},{"id_modelo":"140383135","nombre_modelo":"Magic 5 Lite 5G 8GB\/256GB 6.7\u00b4\u00b4 Dual Sim","nombre_modelo_eng":"Magic 5 Lite 5G 8GB\/256GB 6.7\u00b4\u00b4 Dual Sim","marca":"Honor","sostenible":0,"productes":[{"brut":"217.30","v360":null,"talla":null,"color":null,"v180":null,"talla2":null,"talla_usa":null,"talla_uk":null,"talla_jp":null,"stock_reservat":0,"v90":null,"desc_brand":"0.00","exist":0,"rec":"462.63","pmp":"217.30","v30":null,"id_producte":"141322044","baja":"0","referencia":"5109ARUJ","sellers":[]}],"familias":null,"video_mp4":0,"fecha_descatalogado":"2078-12-31T00:00:00","image_created":null,"tres_sesenta":"0","precio_win":262.49,"id_pos_producte_win":0,"id_marca":"4341","precio_tachado":0,"list_atributos":""},{"id_modelo":"140231852","nombre_modelo":"Edge 30 Neo 8GB\/128GB 6.3\u00b4\u00b4 Dual Sim Refurbished","nombre_modelo_eng":"Edge 30 Neo 8GB\/128GB 6.3\u00b4\u00b4 Dual Sim Refurbished","marca":"Motorola","sostenible":0,"productes":[{"brut":"329.75","v360":null,"talla":null,"color":null,"v180":null,"talla2":null,"talla_usa":null,"talla_uk":null,"talla_jp":null,"stock_reservat":0,"v90":null,"desc_brand":"0.00","exist":1,"rec":"499.70","pmp":"329.75","v30":null,"id_producte":"140842422","baja":"0","referencia":"R-17792696-PAV00072FR","sellers":[]}],"familias":null,"video_mp4":0,"fecha_descatalogado":"1992-05-20T00:00:00","image_created":null,"tres_sesenta":"0","precio_win":264.49,"id_pos_producte_win":0,"id_marca":"2180","precio_tachado":0,"list_atributos":""},{"id_modelo":"140333503","nombre_modelo":"Poco X5 Pro 5G 6GB\/128GB 6.67\u00b4\u00b4 Dual Sim","nombre_modelo_eng":"Poco X5 Pro 5G 6GB\/128GB 6.67\u00b4\u00b4 Dual Sim","marca":"Xiaomi","sostenible":0,"productes":[{"brut":"229.95","v360":null,"talla":null,"color":null,"v180":null,"talla2":null,"talla_usa":null,"talla_uk":null,"talla_jp":null,"stock_reservat":0,"v90":null,"desc_brand":"0.00","exist":0,"rec":"361.08","pmp":"229.95","v30":null,"id_producte":"141160492","baja":"0","referencia":"MZB0CRLEU","sellers":[]}],"familias":null,"video_mp4":0,"fecha_descatalogado":"2078-12-31T00:00:00","image_created":null,"tres_sesenta":"0","precio_win":267.99,"id_pos_producte_win":0,"id_marca":"2696","precio_tachado":0,"list_atributos":""},{"id_modelo":"138260351","nombre_modelo":"Redmi Note 10 Pro 6Gb\/64GB 6.6\u00b4\u00b4 Dual Sim","nombre_modelo_eng":"Redmi Note 10 Pro 6Gb\/64GB 6.6\u00b4\u00b4 Dual Sim","marca":"Xiaomi","sostenible":0,"productes":[{"brut":"195.42","v360":null,"talla":null,"color":null,"v180":null,"talla2":null,"talla_usa":null,"talla_uk":null,"talla_jp":null,"stock_reservat":0,"v90":null,"desc_brand":"0.00","exist":1,"rec":"443.05","pmp":"224.50","v30":null,"id_producte":"13834326","baja":"0","referencia":"MZB08KUEU","sellers":[]}],"familias":null,"video_mp4":0,"fecha_descatalogado":"2078-12-31T00:00:00","image_created":null,"tres_sesenta":"1","precio_win":268.49,"id_pos_producte_win":0,"id_marca":"2696","precio_tachado":0,"list_atributos":""},{"id_modelo":"140293523","nombre_modelo":"12 Lite 8GB\/128GB 6.55\u00b4\u00b4 Dual Sim","nombre_modelo_eng":"12 Lite 8GB\/128GB 6.55\u00b4\u00b4 Dual Sim","marca":"Xiaomi","sostenible":0,"productes":[{"brut":"233.10","v360":null,"talla":null,"color":null,"v180":null,"talla2":null,"talla_usa":null,"talla_uk":null,"talla_jp":null,"stock_reservat":0,"v90":null,"desc_brand":"0.00","exist":0,"rec":"370.61","pmp":"233.10","v30":null,"id_producte":"141066112","baja":"0","referencia":"12 L 8-128 GREE","sellers":[]}],"familias":null,"video_mp4":0,"fecha_descatalogado":"2078-12-31T00:00:00","image_created":null,"tres_sesenta":"0","precio_win":271.99,"id_pos_producte_win":0,"id_marca":"2696","precio_tachado":0,"list_atributos":""},{"id_modelo":"139011431","nombre_modelo":"Redmi Note 11 Pro 8GB\/128GB 6.7\u00b4\u00b4 Dual Sim","nombre_modelo_eng":"Redmi Note 11 Pro 8GB\/128GB 6.7\u00b4\u00b4 Dual Sim","marca":"Xiaomi","sostenible":0,"productes":[{"brut":"226.62","v360":null,"talla":null,"color":null,"v180":null,"talla2":null,"talla_usa":null,"talla_uk":null,"talla_jp":null,"stock_reservat":0,"v90":null,"desc_brand":"0.00","exist":0,"rec":"489.08","pmp":"226.62","v30":null,"id_producte":"16521737","baja":"0","referencia":"MZB0AVKEU","sellers":[]}],"familias":null,"video_mp4":0,"fecha_descatalogado":"2078-12-31T00:00:00","image_created":null,"tres_sesenta":"0","precio_win":273.99,"id_pos_producte_win":0,"id_marca":"2696","precio_tachado":0,"list_atributos":""},{"id_modelo":"139861456","nombre_modelo":"Redmi Note 12 Pro 5G 8GB\/128GB 6.67\u00b4\u00b4 Dual Sim","nombre_modelo_eng":"Redmi Note 12 Pro 5G 8GB\/128GB 6.67\u00b4\u00b4 Dual Sim","marca":"Xiaomi","sostenible":0,"productes":[{"brut":"232.98","v360":null,"talla":null,"color":null,"v180":null,"talla2":null,"talla_usa":null,"talla_uk":null,"talla_jp":null,"stock_reservat":0,"v90":null,"desc_brand":"0.00","exist":0,"rec":"400.41","pmp":"232.98","v30":null,"id_producte":"19725321","baja":"0","referencia":"MZB0D2SEU","sellers":[]}],"familias":null,"video_mp4":0,"fecha_descatalogado":"2078-12-31T00:00:00","image_created":null,"tres_sesenta":"0","precio_win":274.49,"id_pos_producte_win":0,"id_marca":"2696","precio_tachado":0,"list_atributos":""},{"id_modelo":"139570562","nombre_modelo":"Edge 30 5G 8GB\/128GB 6.5\u00b4\u00b4 Dual Sim","nombre_modelo_eng":"Edge 30 5G 8GB\/128GB 6.5\u00b4\u00b4 Dual Sim","marca":"Motorola","sostenible":0,"productes":[{"brut":"228.18","v360":null,"talla":null,"color":null,"v180":null,"talla2":null,"talla_usa":null,"talla_uk":null,"talla_jp":null,"stock_reservat":1,"v90":null,"desc_brand":"0.00","exist":0,"rec":"513.85","pmp":"228.18","v30":null,"id_producte":"18607687","baja":"0","referencia":"PAUC0002SE","sellers":[]}],"familias":null,"video_mp4":0,"fecha_descatalogado":"2078-12-31T00:00:00","image_created":null,"tres_sesenta":"0","precio_win":277.49,"id_pos_producte_win":0,"id_marca":"2180","precio_tachado":0,"list_atributos":""},{"id_modelo":"140101999","nombre_modelo":"Galaxy A34 6GB\/128GB 6.6\u00b4\u00b4 Dual Sim","nombre_modelo_eng":"Galaxy A34 6GB\/128GB 6.6\u00b4\u00b4 Dual Sim","marca":"Samsung","sostenible":0,"productes":[{"brut":"228.60","v360":null,"talla":null,"color":null,"v180":null,"talla2":null,"talla_usa":null,"talla_uk":null,"talla_jp":null,"stock_reservat":0,"v90":null,"desc_brand":"0.00","exist":1,"rec":"491.96","pmp":"231.40","v30":null,"id_producte":"140306137","baja":"0","referencia":"SM_A346BLGAEUB","sellers":[]}],"familias":null,"video_mp4":0,"fecha_descatalogado":"2078-12-31T00:00:00","image_created":null,"tres_sesenta":"0","precio_win":278.99,"id_pos_producte_win":0,"id_marca":"2947","precio_tachado":0,"list_atributos":""},{"id_modelo":"139570659","nombre_modelo":"12 Lite 8GB\/128GB 6.5\u00b4\u00b4 Dual Sim","nombre_modelo_eng":"12 Lite 8GB\/128GB 6.5\u00b4\u00b4 Dual Sim","marca":"Xiaomi","sostenible":0,"productes":[{"brut":"230.73","v360":null,"talla":null,"color":null,"v180":null,"talla2":null,"talla_usa":null,"talla_uk":null,"talla_jp":null,"stock_reservat":0,"v90":null,"desc_brand":"0.00","exist":0,"rec":"512.77","pmp":"230.73","v30":null,"id_producte":"18607784","baja":"0","referencia":"40-53-5539","sellers":[]}],"familias":null,"video_mp4":0,"fecha_descatalogado":"2078-12-31T00:00:00","image_created":null,"tres_sesenta":"0","precio_win":279.99,"id_pos_producte_win":0,"id_marca":"2696","precio_tachado":0,"list_atributos":""},{"id_modelo":"139369549","nombre_modelo":"Edge 30 Neo 8GB\/128GB 6.3\u00b4\u00b4 Dual Sim","nombre_modelo_eng":"Edge 30 Neo 8GB\/128GB 6.3\u00b4\u00b4 Dual Sim","marca":"Motorola","sostenible":0,"productes":[{"brut":"226.36","v360":null,"talla":null,"color":null,"v180":null,"talla2":null,"talla_usa":null,"talla_uk":null,"talla_jp":null,"stock_reservat":0,"v90":null,"desc_brand":"0.00","exist":1,"rec":"488.39","pmp":"232.71","v30":null,"id_producte":"17792695","baja":"0","referencia":"PAV00007FR","sellers":[]}],"familias":null,"video_mp4":0,"fecha_descatalogado":"2078-12-31T00:00:00","image_created":null,"tres_sesenta":"1","precio_win":280.49,"id_pos_producte_win":0,"id_marca":"2180","precio_tachado":0,"list_atributos":""},{"id_modelo":"140293534","nombre_modelo":"Redmi Note 11 Pro Plus 5G 8GB\/256GB 6.67\u00b4\u00b4 Dual Sim","nombre_modelo_eng":"Redmi Note 11 Pro Plus 5G 8GB\/256GB 6.67\u00b4\u00b4 Dual Sim","marca":"Xiaomi","sostenible":0,"productes":[{"brut":"253.04","v360":null,"talla":null,"color":null,"v180":null,"talla2":null,"talla_usa":null,"talla_uk":null,"talla_jp":null,"stock_reservat":0,"v90":null,"desc_brand":"0.00","exist":1,"rec":"391.10","pmp":"240.11","v30":null,"id_producte":"141066123","baja":"0","referencia":"MZB0AGFEU","sellers":[]}],"familias":null,"video_mp4":0,"fecha_descatalogado":"2078-12-31T00:00:00","image_created":null,"tres_sesenta":"0","precio_win":280.99,"id_pos_producte_win":0,"id_marca":"2696","precio_tachado":0,"list_atributos":""},{"id_modelo":"139811671","nombre_modelo":"Mi 11T Pro 5G 8GB\/256GB 6.7\u00b4\u00b4 Dual Sim Refurbished","nombre_modelo_eng":"Mi 11T Pro 5G 8GB\/256GB 6.7\u00b4\u00b4 Dual Sim Refurbished","marca":"Xiaomi","sostenible":0,"productes":[{"brut":"332.70","v360":null,"talla":null,"color":null,"v180":null,"talla2":null,"talla_usa":null,"talla_uk":null,"talla_jp":null,"stock_reservat":0,"v90":null,"desc_brand":"0.00","exist":1,"rec":"699.35","pmp":"332.70","v30":null,"id_producte":"19572760","baja":"0","referencia":"R-16521731-MZB09L8EU","sellers":[]}],"familias":null,"video_mp4":0,"fecha_descatalogado":"1992-05-20T00:00:00","image_created":null,"tres_sesenta":"0","precio_win":280.99,"id_pos_producte_win":0,"id_marca":"2696","precio_tachado":0,"list_atributos":""},{"id_modelo":"139889111","nombre_modelo":"Galaxy A34 5G 6GB\/128GB 6.6\u00b4\u00b4 Dual Sim","nombre_modelo_eng":"Galaxy A34 5G 6GB\/128GB 6.6\u00b4\u00b4 Dual Sim","marca":"Samsung","sostenible":0,"productes":[{"brut":"231.40","v360":null,"talla":null,"color":null,"v180":null,"talla2":null,"talla_usa":null,"talla_uk":null,"talla_jp":null,"stock_reservat":0,"v90":null,"desc_brand":"0.00","exist":2,"rec":"491.96","pmp":"234.25","v30":null,"id_producte":"19823543","baja":"0","referencia":"TLSAA34128BLK","sellers":[]}],"familias":null,"video_mp4":0,"fecha_descatalogado":"2078-12-31T00:00:00","image_created":null,"tres_sesenta":"0","precio_win":281.99,"id_pos_producte_win":0,"id_marca":"2947","precio_tachado":0,"list_atributos":""},{"id_modelo":"139358820","nombre_modelo":"BL5000 8\/128GB 6.4\u00b4\u00b4 Dual Sim","nombre_modelo_eng":"BL5000 8\/128GB 6.4\u00b4\u00b4 Dual Sim","marca":"Blackview","sostenible":0,"productes":[{"brut":"218.68","v360":null,"talla":null,"color":null,"v180":null,"talla2":null,"talla_usa":null,"talla_uk":null,"talla_jp":null,"stock_reservat":0,"v90":null,"desc_brand":"0.00","exist":0,"rec":"434.19","pmp":"218.68","v30":null,"id_producte":"17772459","baja":"0","referencia":"BL5000-BK\/BV","sellers":[]}],"familias":null,"video_mp4":0,"fecha_descatalogado":"2078-12-31T00:00:00","image_created":null,"tres_sesenta":"0","precio_win":282.49,"id_pos_producte_win":0,"id_marca":"6610","precio_tachado":0,"list_atributos":""},{"id_modelo":"139011393","nombre_modelo":"Galaxy A33 6GB\/128GB 6.4\u00b4\u00b4 Dual Sim","nombre_modelo_eng":"Galaxy A33 6GB\/128GB 6.4\u00b4\u00b4 Dual Sim","marca":"Samsung","sostenible":0,"productes":[{"brut":"237.00","v360":null,"talla":null,"color":null,"v180":null,"talla2":null,"talla_usa":null,"talla_uk":null,"talla_jp":null,"stock_reservat":0,"v90":null,"desc_brand":"0.00","exist":0,"rec":"453.72","pmp":"237.00","v30":null,"id_producte":"16521699","baja":"0","referencia":"SM-A336BZKGEUB","sellers":[]}],"familias":null,"video_mp4":0,"fecha_descatalogado":"2078-12-31T00:00:00","image_created":null,"tres_sesenta":"1","precio_win":282.49,"id_pos_producte_win":0,"id_marca":"2947","precio_tachado":0,"list_atributos":""},{"id_modelo":"139778653","nombre_modelo":"Redmi Note 12 Pro 5G 8GB\/256GB 6.67\u00b4\u00b4 Dual Sim","nombre_modelo_eng":"Redmi Note 12 Pro 5G 8GB\/256GB 6.67\u00b4\u00b4 Dual Sim","marca":"Xiaomi","sostenible":0,"productes":[{"brut":"233.85","v360":null,"talla":null,"color":null,"v180":null,"talla2":null,"talla_usa":null,"talla_uk":null,"talla_jp":null,"stock_reservat":2,"v90":null,"desc_brand":"0.00","exist":0,"rec":"507.24","pmp":"233.85","v30":null,"id_producte":"19476235","baja":"0","referencia":"903550043","sellers":[]}],"familias":null,"video_mp4":0,"fecha_descatalogado":"2078-12-31T00:00:00","image_created":null,"tres_sesenta":"1","precio_win":282.99,"id_pos_producte_win":0,"id_marca":"2696","precio_tachado":0,"list_atributos":""},{"id_modelo":"139882434","nombre_modelo":"A34 EE 6GB\/128GB 6.6\u00b4\u00b4 Dual Sim","nombre_modelo_eng":"A34 EE 6GB\/128GB 6.6\u00b4\u00b4 Dual Sim","marca":"Samsung","sostenible":0,"productes":[{"brut":"238.24","v360":null,"talla":null,"color":null,"v180":null,"talla2":null,"talla_usa":null,"talla_uk":null,"talla_jp":null,"stock_reservat":0,"v90":null,"desc_brand":"0.00","exist":0,"rec":"464.60","pmp":"238.24","v30":null,"id_producte":"19793828","baja":"0","referencia":"1366729","sellers":[]}],"familias":null,"video_mp4":0,"fecha_descatalogado":"2078-12-31T00:00:00","image_created":null,"tres_sesenta":"0","precio_win":284.49,"id_pos_producte_win":0,"id_marca":"2947","precio_tachado":0,"list_atributos":""},{"id_modelo":"139861457","nombre_modelo":"Redmi Note 12 Pro 5G 8GB\/128GB 6.67\u00b4\u00b4 Dual Sim","nombre_modelo_eng":"Redmi Note 12 Pro 5G 8GB\/128GB 6.67\u00b4\u00b4 Dual Sim","marca":"Xiaomi","sostenible":0,"productes":[{"brut":"228.13","v360":null,"talla":null,"color":null,"v180":null,"talla2":null,"talla_usa":null,"talla_uk":null,"talla_jp":null,"stock_reservat":0,"v90":null,"desc_brand":"0.00","exist":0,"rec":"610.33","pmp":"228.13","v30":null,"id_producte":"19725322","baja":"0","referencia":"MZB0D2TEU","sellers":[]}],"familias":null,"video_mp4":0,"fecha_descatalogado":"2078-12-31T00:00:00","image_created":null,"tres_sesenta":"0","precio_win":284.49,"id_pos_producte_win":0,"id_marca":"2696","precio_tachado":0,"list_atributos":""},{"id_modelo":"139778654","nombre_modelo":"Redmi Note 12 Pro 5G 8GB\/256GB 6.67\u00b4\u00b4 Dual Sim","nombre_modelo_eng":"Redmi Note 12 Pro 5G 8GB\/256GB 6.67\u00b4\u00b4 Dual Sim","marca":"Xiaomi","sostenible":0,"productes":[{"brut":"236.26","v360":null,"talla":null,"color":null,"v180":null,"talla2":null,"talla_usa":null,"talla_uk":null,"talla_jp":null,"stock_reservat":0,"v90":null,"desc_brand":"0.00","exist":0,"rec":"507.24","pmp":"236.26","v30":null,"id_producte":"19476236","baja":"0","referencia":"903550044","sellers":[]}],"familias":null,"video_mp4":0,"fecha_descatalogado":"2078-12-31T00:00:00","image_created":null,"tres_sesenta":"0","precio_win":285.49,"id_pos_producte_win":0,"id_marca":"2696","precio_tachado":0,"list_atributos":""},{"id_modelo":"139899809","nombre_modelo":"Redmi Note 12 Pro 5G 6GB\/128GB 6.67\u00b4\u00b4 Dual Sim","nombre_modelo_eng":"Redmi Note 12 Pro 5G 6GB\/128GB 6.67\u00b4\u00b4 Dual Sim","marca":"Xiaomi","sostenible":0,"productes":[{"brut":"222.25","v360":null,"talla":null,"color":null,"v180":null,"talla2":null,"talla_usa":null,"talla_uk":null,"talla_jp":null,"stock_reservat":0,"v90":null,"desc_brand":"0.00","exist":1,"rec":"360.21","pmp":"246.70","v30":null,"id_producte":"19885955","baja":"0","referencia":"NOTE12P 6-128 WH","sellers":[]}],"familias":null,"video_mp4":0,"fecha_descatalogado":"2078-12-31T00:00:00","image_created":null,"tres_sesenta":"1","precio_win":285.99,"id_pos_producte_win":0,"id_marca":"2696","precio_tachado":0,"list_atributos":""},{"id_modelo":"139899810","nombre_modelo":"Redmi Note 12 Pro 5G 8GB\/256GB 6.67\u00b4\u00b4 Dual Sim","nombre_modelo_eng":"Redmi Note 12 Pro 5G 8GB\/256GB 6.67\u00b4\u00b4 Dual Sim","marca":"Xiaomi","sostenible":0,"productes":[{"brut":"244.65","v360":null,"talla":null,"color":null,"v180":null,"talla2":null,"talla_usa":null,"talla_uk":null,"talla_jp":null,"stock_reservat":1,"v90":null,"desc_brand":"0.00","exist":0,"rec":"389.41","pmp":"244.65","v30":null,"id_producte":"19885956","baja":"0","referencia":"MZB0D2WEU","sellers":[]}],"familias":null,"video_mp4":0,"fecha_descatalogado":"2078-12-31T00:00:00","image_created":null,"tres_sesenta":"0","precio_win":285.99,"id_pos_producte_win":0,"id_marca":"2696","precio_tachado":0,"list_atributos":""},{"id_modelo":"139899748","nombre_modelo":"Galaxy A34 5G 6GB\/128GB 6.6\u00b4\u00b4 Dual Sim","nombre_modelo_eng":"Galaxy A34 5G 6GB\/128GB 6.6\u00b4\u00b4 Dual Sim","marca":"Samsung","sostenible":0,"productes":[{"brut":"238.94","v360":null,"talla":null,"color":null,"v180":null,"talla2":null,"talla_usa":null,"talla_uk":null,"talla_jp":null,"stock_reservat":0,"v90":null,"desc_brand":"0.00","exist":0,"rec":"491.96","pmp":"238.94","v30":null,"id_producte":"19885894","baja":"0","referencia":"SM-A346BLVAEUB","sellers":[]}],"familias":null,"video_mp4":0,"fecha_descatalogado":"2078-12-31T00:00:00","image_created":null,"tres_sesenta":"0","precio_win":286.99,"id_pos_producte_win":0,"id_marca":"2947","precio_tachado":0,"list_atributos":""},{"id_modelo":"139562232","nombre_modelo":"8GB\/256GB 6.6\u00b4\u00b4 Dual Sim","nombre_modelo_eng":"8GB\/256GB 6.6\u00b4\u00b4 Dual Sim","marca":"Ulefone","sostenible":0,"productes":[{"brut":"227.71","v360":null,"talla":null,"color":null,"v180":null,"talla2":null,"talla_usa":null,"talla_uk":null,"talla_jp":null,"stock_reservat":0,"v90":null,"desc_brand":"0.00","exist":0,"rec":"396.54","pmp":"227.71","v30":null,"id_producte":"18575481","baja":"0","referencia":"1362019","sellers":[]}],"familias":null,"video_mp4":0,"fecha_descatalogado":"2078-12-31T00:00:00","image_created":null,"tres_sesenta":"0","precio_win":287.49,"id_pos_producte_win":0,"id_marca":"6373","precio_tachado":0,"list_atributos":""},{"id_modelo":"139778652","nombre_modelo":"Redmi Note 12 Pro 5G 8GB\/128GB 6.67\u00b4\u00b4 Dual Sim","nombre_modelo_eng":"Redmi Note 12 Pro 5G 8GB\/128GB 6.67\u00b4\u00b4 Dual Sim","marca":"Xiaomi","sostenible":0,"productes":[{"brut":"228.13","v360":null,"talla":null,"color":null,"v180":null,"talla2":null,"talla_usa":null,"talla_uk":null,"talla_jp":null,"stock_reservat":0,"v90":null,"desc_brand":"0.00","exist":2,"rec":"460.77","pmp":"241.31","v30":null,"id_producte":"19476234","baja":"0","referencia":"903548830","sellers":[]}],"familias":null,"video_mp4":0,"fecha_descatalogado":"2078-12-31T00:00:00","image_created":null,"tres_sesenta":"0","precio_win":287.49,"id_pos_producte_win":0,"id_marca":"2696","precio_tachado":0,"list_atributos":""},{"id_modelo":"140333464","nombre_modelo":"A98 5G 8GB\/256GB 6.72\u00b4\u00b4 Dual Sim","nombre_modelo_eng":"A98 5G 8GB\/256GB 6.72\u00b4\u00b4 Dual Sim","marca":"Oppo","sostenible":0,"productes":[{"brut":"225.75","v360":null,"talla":null,"color":null,"v180":null,"talla2":null,"talla_usa":null,"talla_uk":null,"talla_jp":null,"stock_reservat":1,"v90":null,"desc_brand":"0.00","exist":0,"rec":"415.12","pmp":"225.75","v30":null,"id_producte":"141160453","baja":"0","referencia":"OPPO-6932169329149","sellers":[]}],"familias":null,"video_mp4":0,"fecha_descatalogado":"2078-12-31T00:00:00","image_created":null,"tres_sesenta":"0","precio_win":287.99,"id_pos_producte_win":0,"id_marca":"4981","precio_tachado":0,"list_atributos":""},{"id_modelo":"139859545","nombre_modelo":"iPhone 7 2GB\/32GB 4.7\u00b4\u00b4 Dual Sim Refurbished","nombre_modelo_eng":"iPhone 7 2GB\/32GB 4.7\u00b4\u00b4 Dual Sim Refurbished","marca":"Apple","sostenible":0,"productes":[{"brut":"247.68","v360":null,"talla":null,"color":null,"v180":null,"talla2":null,"talla_usa":null,"talla_uk":null,"talla_jp":null,"stock_reservat":0,"v90":null,"desc_brand":"0.00","exist":0,"rec":"376.47","pmp":"247.68","v30":null,"id_producte":"19720301","baja":"0","referencia":"1364073","sellers":[]}],"familias":null,"video_mp4":0,"fecha_descatalogado":"2078-12-31T00:00:00","image_created":null,"tres_sesenta":"0","precio_win":287.99,"id_pos_producte_win":0,"id_marca":"4321","precio_tachado":0,"list_atributos":""},{"id_modelo":"139693173","nombre_modelo":"Construction 6GB\/128GB 6\u00b4\u00b4 Dual Sim","nombre_modelo_eng":"Construction 6GB\/128GB 6\u00b4\u00b4 Dual Sim","marca":"Hammer","sostenible":0,"productes":[{"brut":"231.85","v360":null,"talla":null,"color":null,"v180":null,"talla2":null,"talla_usa":null,"talla_uk":null,"talla_jp":null,"stock_reservat":0,"v90":null,"desc_brand":"0.00","exist":0,"rec":"367.98","pmp":"231.85","v30":null,"id_producte":"19126022","baja":"0","referencia":"TLHACONSTRUC","sellers":[]}],"familias":null,"video_mp4":0,"fecha_descatalogado":"2078-12-31T00:00:00","image_created":null,"tres_sesenta":"0","precio_win":288.49,"id_pos_producte_win":0,"id_marca":"5337","precio_tachado":0,"list_atributos":""},{"id_modelo":"140293533","nombre_modelo":"Redmi Note 11 Pro Plus 5G 8GB\/256GB 6.67\u00b4\u00b4 Dual Sim","nombre_modelo_eng":"Redmi Note 11 Pro Plus 5G 8GB\/256GB 6.67\u00b4\u00b4 Dual Sim","marca":"Xiaomi","sostenible":0,"productes":[{"brut":"256.42","v360":null,"talla":null,"color":null,"v180":null,"talla2":null,"talla_usa":null,"talla_uk":null,"talla_jp":null,"stock_reservat":0,"v90":null,"desc_brand":"0.00","exist":0,"rec":"400.37","pmp":"256.42","v30":null,"id_producte":"141066122","baja":"0","referencia":"NOTE11PP 5G8-256GREV2","sellers":[]}],"familias":null,"video_mp4":0,"fecha_descatalogado":"2078-12-31T00:00:00","image_created":null,"tres_sesenta":"0","precio_win":298.99,"id_pos_producte_win":0,"id_marca":"2696","precio_tachado":0,"list_atributos":""},{"id_modelo":"139889112","nombre_modelo":"Galaxy A34 5G 6GB\/128GB 6.6\u00b4\u00b4 Dual Sim","nombre_modelo_eng":"Galaxy A34 5G 6GB\/128GB 6.6\u00b4\u00b4 Dual Sim","marca":"Samsung","sostenible":0,"productes":[{"brut":"231.40","v360":null,"talla":null,"color":null,"v180":null,"talla2":null,"talla_usa":null,"talla_uk":null,"talla_jp":null,"stock_reservat":0,"v90":null,"desc_brand":"0.00","exist":1,"rec":"491.96","pmp":"252.57","v30":null,"id_producte":"19823544","baja":"0","referencia":"TLSAA34128ASI","sellers":[]}],"familias":null,"video_mp4":0,"fecha_descatalogado":"2078-12-31T00:00:00","image_created":null,"tres_sesenta":"0","precio_win":301.49,"id_pos_producte_win":0,"id_marca":"2947","precio_tachado":0,"list_atributos":""},{"id_modelo":"139954007","nombre_modelo":"POCO X5 Pro 5G 8GB\/256GB 6.67\u00b4\u00b4 Dual Sim","nombre_modelo_eng":"POCO X5 Pro 5G 8GB\/256GB 6.67\u00b4\u00b4 Dual Sim","marca":"Xiaomi","sostenible":0,"productes":[{"brut":"259.39","v360":null,"talla":null,"color":null,"v180":null,"talla2":null,"talla_usa":null,"talla_uk":null,"talla_jp":null,"stock_reservat":0,"v90":null,"desc_brand":"0.00","exist":0,"rec":"399.00","pmp":"259.39","v30":null,"id_producte":"139825194","baja":"0","referencia":"POCO X5 P 5G 8-256 BK","sellers":[]}],"familias":null,"video_mp4":0,"fecha_descatalogado":"2078-12-31T00:00:00","image_created":null,"tres_sesenta":"0","precio_win":301.99,"id_pos_producte_win":0,"id_marca":"2696","precio_tachado":0,"list_atributos":""},{"id_modelo":"140293529","nombre_modelo":"POCO X5 Pro 5G 8GB\/256GB 6.67\u00b4\u00b4 Dual Sim","nombre_modelo_eng":"POCO X5 Pro 5G 8GB\/256GB 6.67\u00b4\u00b4 Dual Sim","marca":"Xiaomi","sostenible":0,"productes":[{"brut":"259.38","v360":null,"talla":null,"color":null,"v180":null,"talla2":null,"talla_usa":null,"talla_uk":null,"talla_jp":null,"stock_reservat":0,"v90":null,"desc_brand":"0.00","exist":0,"rec":"395.02","pmp":"259.38","v30":null,"id_producte":"141066118","baja":"0","referencia":"POCO X5 P 5G 8-256 YE","sellers":[]}],"familias":null,"video_mp4":0,"fecha_descatalogado":"2078-12-31T00:00:00","image_created":null,"tres_sesenta":"0","precio_win":301.99,"id_pos_producte_win":0,"id_marca":"2696","precio_tachado":0,"list_atributos":""},{"id_modelo":"139889076","nombre_modelo":"iPhone XR 64GB 6.1\u00b4\u00b4 Dual Sim Refurbished AB","nombre_modelo_eng":"iPhone XR 64GB 6.1\u00b4\u00b4 Dual Sim Refurbished AB","marca":"Apple","sostenible":0,"productes":[{"brut":"219.95","v360":null,"talla":null,"color":null,"v180":null,"talla2":null,"talla_usa":null,"talla_uk":null,"talla_jp":null,"stock_reservat":0,"v90":null,"desc_brand":"0.00","exist":0,"rec":"349.52","pmp":"219.95","v30":null,"id_producte":"19823508","baja":"0","referencia":"SLIPXR64REDA","sellers":[]}],"familias":null,"video_mp4":0,"fecha_descatalogado":"2078-12-31T00:00:00","image_created":null,"tres_sesenta":"0","precio_win":304.99,"id_pos_producte_win":0,"id_marca":"4321","precio_tachado":0,"list_atributos":""},{"id_modelo":"139780492","nombre_modelo":"Galaxy A53 Enterprise Edition 8GB\/128GB 6.5\u00b4\u00b4 Dual Sim","nombre_modelo_eng":"Galaxy A53 Enterprise Edition 8GB\/128GB 6.5\u00b4\u00b4 Dual Sim","marca":"Samsung","sostenible":0,"productes":[{"brut":"259.70","v360":null,"talla":null,"color":null,"v180":null,"talla2":null,"talla_usa":null,"talla_uk":null,"talla_jp":null,"stock_reservat":0,"v90":null,"desc_brand":"0.00","exist":0,"rec":"469.68","pmp":"259.70","v30":null,"id_producte":"19480373","baja":"0","referencia":"SM-A536BZKNEEE","sellers":[]}],"familias":null,"video_mp4":0,"fecha_descatalogado":"2078-12-31T00:00:00","image_created":null,"tres_sesenta":"0","precio_win":307.49,"id_pos_producte_win":0,"id_marca":"2947","precio_tachado":0,"list_atributos":""},{"id_modelo":"139859549","nombre_modelo":"iPhone 7 2GB\/32GB 6\u00b4\u00b4 Dual Sim Refurbished","nombre_modelo_eng":"iPhone 7 2GB\/32GB 6\u00b4\u00b4 Dual Sim Refurbished","marca":"Apple","sostenible":0,"productes":[{"brut":"247.68","v360":null,"talla":null,"color":null,"v180":null,"talla2":null,"talla_usa":null,"talla_uk":null,"talla_jp":null,"stock_reservat":0,"v90":null,"desc_brand":"0.00","exist":0,"rec":"376.47","pmp":"247.68","v30":null,"id_producte":"19720305","baja":"0","referencia":"1364074","sellers":[]}],"familias":null,"video_mp4":0,"fecha_descatalogado":"2078-12-31T00:00:00","image_created":null,"tres_sesenta":"0","precio_win":311.99,"id_pos_producte_win":0,"id_marca":"4321","precio_tachado":0,"list_atributos":""},{"id_modelo":"139859547","nombre_modelo":"iPhone 7 2GB\/32GB 4.7\u00b4\u00b4 Dual Sim Refurbished","nombre_modelo_eng":"iPhone 7 2GB\/32GB 4.7\u00b4\u00b4 Dual Sim Refurbished","marca":"Apple","sostenible":0,"productes":[{"brut":"247.68","v360":null,"talla":null,"color":null,"v180":null,"talla2":null,"talla_usa":null,"talla_uk":null,"talla_jp":null,"stock_reservat":0,"v90":null,"desc_brand":"0.00","exist":0,"rec":"376.47","pmp":"247.68","v30":null,"id_producte":"19720303","baja":"0","referencia":"1364076","sellers":[]}],"familias":null,"video_mp4":0,"fecha_descatalogado":"2078-12-31T00:00:00","image_created":null,"tres_sesenta":"0","precio_win":311.99,"id_pos_producte_win":0,"id_marca":"4321","precio_tachado":0,"list_atributos":""},{"id_modelo":"139859548","nombre_modelo":"iPhone 7 2GB\/32GB 4.7\u00b4\u00b4 Dual Sim Refurbished","nombre_modelo_eng":"iPhone 7 2GB\/32GB 4.7\u00b4\u00b4 Dual Sim Refurbished","marca":"Apple","sostenible":0,"productes":[{"brut":"247.68","v360":null,"talla":null,"color":null,"v180":null,"talla2":null,"talla_usa":null,"talla_uk":null,"talla_jp":null,"stock_reservat":0,"v90":null,"desc_brand":"0.00","exist":0,"rec":"376.47","pmp":"247.68","v30":null,"id_producte":"19720304","baja":"0","referencia":"1364075","sellers":[]}],"familias":null,"video_mp4":0,"fecha_descatalogado":"2078-12-31T00:00:00","image_created":null,"tres_sesenta":"0","precio_win":311.99,"id_pos_producte_win":0,"id_marca":"4321","precio_tachado":0,"list_atributos":""}],"categorias":[{"nombre_familia":"Phones","subfamilias":[{"nombre_subfamilia":"Accessories","ids_subfamilias":[15811],"num_prods_subfamilia":721,"copy_talla":null,"copy_talla2":null,"ids_atributo_show":"755,744","no_mostrar_talla":1},{"nombre_subfamilia":"Basic mobile phones","ids_subfamilias":[15808],"num_prods_subfamilia":133,"copy_talla":null,"copy_talla2":"Plug Type","ids_atributo_show":"1005","no_mostrar_talla":1},{"nombre_subfamilia":"Cases and covers","ids_subfamilias":[15810],"num_prods_subfamilia":2609,"copy_talla":null,"copy_talla2":null,"ids_atributo_show":"1060,962,695","no_mostrar_talla":1},{"nombre_subfamilia":"Chargers","ids_subfamilias":[16338],"num_prods_subfamilia":695,"copy_talla":null,"copy_talla2":"Plug Type","ids_atributo_show":"988,1055","no_mostrar_talla":1},{"nombre_subfamilia":"Headphones","ids_subfamilias":[16224],"num_prods_subfamilia":1081,"copy_talla":null,"copy_talla2":null,"ids_atributo_show":"695,964","no_mostrar_talla":1},{"nombre_subfamilia":"Home phones","ids_subfamilias":[15809],"num_prods_subfamilia":254,"copy_talla":null,"copy_talla2":null,"ids_atributo_show":"957","no_mostrar_talla":1},{"nombre_subfamilia":"Microsd cards","ids_subfamilias":[16574],"num_prods_subfamilia":285,"copy_talla":null,"copy_talla2":null,"ids_atributo_show":"978","no_mostrar_talla":1},{"nombre_subfamilia":"Mobile phones","ids_subfamilias":[15806],"num_prods_subfamilia":779,"copy_talla":null,"copy_talla2":"Plug Type","ids_atributo_show":"1064,695,996,978,999,980,984,1005,985","no_mostrar_talla":1},{"nombre_subfamilia":"Power banks","ids_subfamilias":[16163],"num_prods_subfamilia":183,"copy_talla":null,"copy_talla2":null,"ids_atributo_show":"695,985","no_mostrar_talla":1},{"nombre_subfamilia":"Professional telephones","ids_subfamilias":[16023],"num_prods_subfamilia":231,"copy_talla":null,"copy_talla2":null,"ids_atributo_show":null,"no_mostrar_talla":1},{"nombre_subfamilia":"Screen protectors","ids_subfamilias":[16239],"num_prods_subfamilia":974,"copy_talla":null,"copy_talla2":null,"ids_atributo_show":"744,962","no_mostrar_talla":1},{"nombre_subfamilia":"Smartwatches","ids_subfamilias":[15885],"num_prods_subfamilia":310,"copy_talla":null,"copy_talla2":null,"ids_atributo_show":"863,1064,771,695","no_mostrar_talla":1},{"nombre_subfamilia":"Speakers","ids_subfamilias":[16309],"num_prods_subfamilia":474,"copy_talla":null,"copy_talla2":null,"ids_atributo_show":"695","no_mostrar_talla":1}]}],"marcas":[{"marca":"Alcatel","id_marca":2922,"num_prods_marca":5},{"marca":"Apple","id_marca":4321,"num_prods_marca":203},{"marca":"Asus","id_marca":4382,"num_prods_marca":2},{"marca":"Blackview","id_marca":6610,"num_prods_marca":1},{"marca":"Bullit","id_marca":12363,"num_prods_marca":1},{"marca":"Cat","id_marca":3923,"num_prods_marca":2},{"marca":"Crosscall","id_marca":4401,"num_prods_marca":6},{"marca":"Cubot","id_marca":4980,"num_prods_marca":9},{"marca":"Doro","id_marca":5338,"num_prods_marca":4},{"marca":"Energizer","id_marca":1475,"num_prods_marca":2},{"marca":"Fairphone","id_marca":5265,"num_prods_marca":1},{"marca":"Gigaset","id_marca":4347,"num_prods_marca":5},{"marca":"Google","id_marca":4400,"num_prods_marca":13},{"marca":"Hammer","id_marca":5337,"num_prods_marca":11},{"marca":"Honor","id_marca":4341,"num_prods_marca":24},{"marca":"Huawei","id_marca":3180,"num_prods_marca":2},{"marca":"Motorola","id_marca":2180,"num_prods_marca":50},{"marca":"Nokia","id_marca":3406,"num_prods_marca":5},{"marca":"Nomu","id_marca":7416,"num_prods_marca":1},{"marca":"Nothing phone","id_marca":12882,"num_prods_marca":3},{"marca":"Nubia","id_marca":13213,"num_prods_marca":2},{"marca":"Olympia","id_marca":6030,"num_prods_marca":2},{"marca":"Oneplus","id_marca":6169,"num_prods_marca":4},{"marca":"Oppo","id_marca":4981,"num_prods_marca":30},{"marca":"Oukitel","id_marca":12158,"num_prods_marca":10},{"marca":"Qubo","id_marca":5546,"num_prods_marca":5},{"marca":"Realme","id_marca":4972,"num_prods_marca":17},{"marca":"SPC","id_marca":2695,"num_prods_marca":9},{"marca":"Samsung","id_marca":2947,"num_prods_marca":149},{"marca":"Sonstige","id_marca":9179,"num_prods_marca":2},{"marca":"Tcl","id_marca":4982,"num_prods_marca":18},{"marca":"Telecom","id_marca":5485,"num_prods_marca":2},{"marca":"Ulefone","id_marca":6373,"num_prods_marca":22},{"marca":"Vivo","id_marca":5560,"num_prods_marca":7},{"marca":"Xiaomi","id_marca":2696,"num_prods_marca":130},{"marca":"Zte","id_marca":4345,"num_prods_marca":20}],"tallas":[{"talla":"One Size","num_prods_talla":779}],"tallas_pais":[],"tallas_2":[{"talla":"EU Plug","num_prods_talla":19}],"atributos":[{"id_atributo":1005,"nombre_atributo":"Sim","atributos_valores":[{"nombre_atributo_valor":"Dual","id_atributo_valor":5590,"num_prods_atributo":711},{"nombre_atributo_valor":"Single","id_atributo_valor":5589,"num_prods_atributo":58}],"operador":"1","prioritat":"0"},{"id_atributo":1064,"nombre_atributo":"Product Aspect","atributos_valores":[{"nombre_atributo_valor":"New","id_atributo_valor":7024,"num_prods_atributo":727},{"nombre_atributo_valor":"Refurbished","id_atributo_valor":7025,"num_prods_atributo":58}],"operador":"1","prioritat":"0"},{"id_atributo":999,"nombre_atributo":"Inches","atributos_valores":[{"nombre_atributo_valor":"4.0-4.4","id_atributo_valor":5573,"num_prods_atributo":3},{"nombre_atributo_valor":"4.5-4.9","id_atributo_valor":5540,"num_prods_atributo":20},{"nombre_atributo_valor":"5.0-5.4","id_atributo_valor":5541,"num_prods_atributo":35},{"nombre_atributo_valor":"5.5-5.9","id_atributo_valor":5542,"num_prods_atributo":45},{"nombre_atributo_valor":"6.0-6.4","id_atributo_valor":5543,"num_prods_atributo":224},{"nombre_atributo_valor":"6.5-6.9","id_atributo_valor":5544,"num_prods_atributo":442},{"nombre_atributo_valor":"7.0-9.9","id_atributo_valor":7856,"num_prods_atributo":8}],"operador":"1","prioritat":"1"},{"id_atributo":996,"nombre_atributo":"Connectivities","atributos_valores":[{"nombre_atributo_valor":"3G","id_atributo_valor":5378,"num_prods_atributo":73},{"nombre_atributo_valor":"4G","id_atributo_valor":5379,"num_prods_atributo":516},{"nombre_atributo_valor":"5G","id_atributo_valor":6846,"num_prods_atributo":422},{"nombre_atributo_valor":"Bluetooth","id_atributo_valor":5373,"num_prods_atributo":617},{"nombre_atributo_valor":"GPS","id_atributo_valor":5374,"num_prods_atributo":297},{"nombre_atributo_valor":"NFC","id_atributo_valor":5375,"num_prods_atributo":353},{"nombre_atributo_valor":"Wi-Fi","id_atributo_valor":5377,"num_prods_atributo":473}],"operador":"0","prioritat":"2"},{"id_atributo":978,"nombre_atributo":"Storage","atributos_valores":[{"nombre_atributo_valor":"1 TB","id_atributo_valor":5390,"num_prods_atributo":11},{"nombre_atributo_valor":"128 GB","id_atributo_valor":5475,"num_prods_atributo":276},{"nombre_atributo_valor":"16 GB","id_atributo_valor":5472,"num_prods_atributo":10},{"nombre_atributo_valor":"256 GB","id_atributo_valor":5476,"num_prods_atributo":186},{"nombre_atributo_valor":"32 GB","id_atributo_valor":5473,"num_prods_atributo":103},{"nombre_atributo_valor":"512 GB","id_atributo_valor":5471,"num_prods_atributo":55},{"nombre_atributo_valor":"64 GB","id_atributo_valor":5474,"num_prods_atributo":138}],"operador":"1","prioritat":"3"},{"id_atributo":985,"nombre_atributo":"Batteries","atributos_valores":[{"nombre_atributo_valor":"1000-2000 mAh","id_atributo_valor":5487,"num_prods_atributo":19},{"nombre_atributo_valor":"2001-3000 mAh","id_atributo_valor":5488,"num_prods_atributo":86},{"nombre_atributo_valor":"3001-4000 mAh","id_atributo_valor":5489,"num_prods_atributo":103},{"nombre_atributo_valor":"4001-5000 mAh","id_atributo_valor":5490,"num_prods_atributo":520},{"nombre_atributo_valor":"5001-6000 mAh","id_atributo_valor":5491,"num_prods_atributo":33},{"nombre_atributo_valor":"6001-7000 mAh","id_atributo_valor":5492,"num_prods_atributo":11},{"nombre_atributo_valor":"7001-8000 mAh","id_atributo_valor":5493,"num_prods_atributo":1},{"nombre_atributo_valor":">8000 mAh","id_atributo_valor":5494,"num_prods_atributo":4}],"operador":"1","prioritat":"3"},{"id_atributo":984,"nombre_atributo":"Operating System","atributos_valores":[{"nombre_atributo_valor":"Android","id_atributo_valor":5334,"num_prods_atributo":576},{"nombre_atributo_valor":"iOS","id_atributo_valor":5335,"num_prods_atributo":203}],"operador":"1","prioritat":"8"},{"id_atributo":980,"nombre_atributo":"RAM","atributos_valores":[{"nombre_atributo_valor":"1 GB","id_atributo_valor":8450,"num_prods_atributo":9},{"nombre_atributo_valor":"12 GB","id_atributo_valor":5480,"num_prods_atributo":38},{"nombre_atributo_valor":"16 GB","id_atributo_valor":5403,"num_prods_atributo":4},{"nombre_atributo_valor":"2 GB","id_atributo_valor":5400,"num_prods_atributo":54},{"nombre_atributo_valor":"3 GB","id_atributo_valor":5478,"num_prods_atributo":74},{"nombre_atributo_valor":"4 GB","id_atributo_valor":5401,"num_prods_atributo":215},{"nombre_atributo_valor":"6 GB","id_atributo_valor":5479,"num_prods_atributo":196},{"nombre_atributo_valor":"8 GB","id_atributo_valor":5402,"num_prods_atributo":188},{"nombre_atributo_valor":"<2 GB","id_atributo_valor":5484,"num_prods_atributo":1}],"operador":"1","prioritat":"9"},{"id_atributo":695,"nombre_atributo":"Color","atributos_valores":[{"nombre_atributo_valor":"Beige","id_atributo_valor":2168,"num_prods_atributo":16},{"nombre_atributo_valor":"Black","id_atributo_valor":2178,"num_prods_atributo":236},{"nombre_atributo_valor":"Blue","id_atributo_valor":2177,"num_prods_atributo":147},{"nombre_atributo_valor":"Brown","id_atributo_valor":2172,"num_prods_atributo":2},{"nombre_atributo_valor":"Clear","id_atributo_valor":2169,"num_prods_atributo":6},{"nombre_atributo_valor":"Golden","id_atributo_valor":2227,"num_prods_atributo":16},{"nombre_atributo_valor":"Green","id_atributo_valor":2170,"num_prods_atributo":78},{"nombre_atributo_valor":"Grey","id_atributo_valor":2179,"num_prods_atributo":88},{"nombre_atributo_valor":"Multicolor","id_atributo_valor":2173,"num_prods_atributo":1},{"nombre_atributo_valor":"Orange","id_atributo_valor":2176,"num_prods_atributo":7},{"nombre_atributo_valor":"Pink","id_atributo_valor":2226,"num_prods_atributo":13},{"nombre_atributo_valor":"Purple","id_atributo_valor":2180,"num_prods_atributo":40},{"nombre_atributo_valor":"Red","id_atributo_valor":2174,"num_prods_atributo":34},{"nombre_atributo_valor":"Silver","id_atributo_valor":2228,"num_prods_atributo":33},{"nombre_atributo_valor":"White","id_atributo_valor":2175,"num_prods_atributo":59},{"nombre_atributo_valor":"Yellow","id_atributo_valor":2171,"num_prods_atributo":9}],"operador":"1","prioritat":"10"}]}